Workbook

Sheet Cover Page
B1: ASIAN PAINTS LIMITED
B2: Financial Model | FY2021 - FY2030E
B4: SNAPSHOT
B5: FY2025 (Latest Actual) | E5: FY2030E (Forecast)
B6: Revenue | C6: EBITDA | D6: PAT | E6: Revenue | G6: EPS (Basic)
B7: ='Income Statement & Forecast'!G10 -> 34478.23 | C7: ='Income Statement & Forecast'!G18 -> 6578.82 | D7: ='Income Statement & Forecast'!G31 -> 3709.71 | E7: ='Income Statement & Forecast'!M10 -> 49243.175 | G7: ='Income Statement & Forecast'!M47 -> 58.218966
B8: ₹ Crores | C8: ₹ Crores | D8: ₹ Crores | E8: ₹ Crores | G8: ₹ per share
B10: Revenue 5Y CAGR | C10: =('Income Statement & Forecast'!M10/'Income Statement & Forecast'!G10)^(1/5)-1 -> 0.073891035 | D10: PAT 5Y CAGR | E10: =('Income Statement & Forecast'!M31/'Income Statement & Forecast'!G31)^(1/5)-1 -> 0.087755792
B12: MODEL DETAILS
B13: Company | C13: Asian Paints Limited
B14: Industry | C14: Paints, Coatings & Home Décor
B15: Reporting Currency | C15: Indian Rupees (₹), values in ₹ Crores
B16: Historical Period | C16: FY2021 - FY2025 (5 years actual)
B17: Forecast Period | C17: FY2026E - FY2030E (5 years forecast)
B18: Last Updated | C18: =TODAY() -> 46151
B20: TABLE OF CONTENTS
B21: Sheet | C21: Description
B22: =HYPERLINK("#'Cover Page'!B1","→ Cover Page") -> → Cover Page | C22: Model overview, navigation, and formatting legend
B23: =HYPERLINK("#Summary!B1","→ Summary") -> → Summary | C23: Key financial highlights, ratios, and KPIs across periods
B24: =HYPERLINK("#Assumptions!B1","→ Assumptions") -> → Assumptions | C24: Forecast drivers - growth rates, margins, working capital days
B25: =HYPERLINK("#'Income Statement & Forecast'!B1","→ Income Statement") -> → Income Statement | C25: Consolidated P&L - actuals and forecasts
B26: =HYPERLINK("#'Balance Sheet & Forecast'!B1","→ Balance Sheet") -> → Balance Sheet | C26: Consolidated balance sheet - actuals and forecasts
B27: =HYPERLINK("#'Cash Flow Statement & Forecast'!B1","→ Cash Flow Statement") -> → Cash Flow Statement | C27: Consolidated cash flows - actuals and forecasts
B29: FORMATTING LEGEND
B30: Format | C30: Meaning
B31: 1234.56 | C31: Hardcoded forecast input (manually entered assumption)
B32: 1234.56 | C32: Forecast formula (forward-looking calculation)
B33: SECTION HEADER | C33: Major section divider
B34: 1234.56 | C34: Subtotal/Total (bold with double bottom border)
B35: 0 | C35: Balance Check (must equal 0; red flag if non-zero)
B37: MODEL NOTES
B38: Forecast methodology | C38: Revenue grown by assumed annual rates; expenses driven by % of revenue
B39: Working capital | C39: Forecast based on assumed Days Sales / Inventory / Payables Outstanding
B40: Cash flow plug | C40: Cash position is the balancing plug; may turn negative under base assumptions
B43: Source: Asia paints Ltd. Annual Reports FY21-FY25; NSE/BSE filings; brokerage research; management Q4 FY26 commentary
B44: Prepared as part of independent academic / analytical exercise
B45: Disclaimer: This valuation is for illustrative & educational purposes only. It does not constitute investment advice, recommendation, or solicitation.
B46: All figures are model outputs subject to assumptions; actual results may differ materially.

Sheet Instructions
B1: ASIAN PAINTS LIMITED
B2: User Guide & Instructions
B4: 1 | C4: PURPOSE OF THIS MODEL
D6: Asian Paints Limited — a 5-year integrated financial forecasting model.
D7: • 5 years of historical actuals (FY2021 - FY2025)
D8: • 5 years of forecast projections (FY2026E - FY2030E)
D9: • Three linked statements (Income Statement, Balance Sheet, Cash Flow) driven by a single Assumptions sheet
D10: • Interactive Cover Page and Summary dashboards with year-pickers and KPI tiles
B11: 2 | C11: HOW TO USE
B13: Step 1 | C13: Open Cover Page | D13: Pick a fiscal year in cell C6 to refresh the KPI snapshot tiles instantly.
B14: Step 2 | C14: Open Summary | D14: Use year picker (C4) and compare-to picker (F4) for YoY deltas with arrows.
B15: Step 3 | C15: Edit Assumptions | D15: All forecast drivers live here — yellow input cells are editable.
B16: Step 4 | C16: Trace through statements | D16: IS → BS → CF flow downstream from Assumptions automatically.
B17: Step 5 | C17: Verify balance check | D17: Balance Sheet row 65 must equal 0 across all periods (red if non-zero).
B18: Step 6 | C18: Inspect charts | D18: Summary holds two interactive charts (rows 53-70) sourced from helper data.
B20: 3 | C20: SHEET MAP
B22: Sheet | C22: Name | D22: Description
B23: • | C23: =HYPERLINK("#'Cover Page'!B1","Cover Page") -> Cover Page | D23: Brand snapshot, year-picker KPI tiles, revenue chart, navigation hub.
B24: • | C24: =HYPERLINK("#Instructions!B1","Instructions") -> Instructions | D24: You are here — user guide and conventions reference.
B25: • | C25: =HYPERLINK("#Summary!B1","Summary") -> Summary | D25: Executive dashboard, KPIs, ratios, YoY deltas, two charts.
B26: • | C26: =HYPERLINK("#Assumptions!B1","Assumptions") -> Assumptions | D26: All forecast drivers — growth, margins, working capital days. Edit here.
B27: • | C27: =HYPERLINK("#'Income Statement & Forecast'!B1","Income Statement") -> Income Statement | D27: Consolidated P&L — actuals through FY25, forecasts FY26E-FY30E.
B28: • | C28: =HYPERLINK("#'Balance Sheet & Forecast'!B1","Balance Sheet") -> Balance Sheet | D28: Assets, equity, liabilities. Includes balance check on row 65.
B29: • | C29: =HYPERLINK("#'Cash Flow Statement & Forecast'!B1","Cash Flow Statement") -> Cash Flow Statement | D29: Operating, investing, financing flows. Cash position is the plug.
B31: 4 | C31: INTERACTIVE FEATURES
B33: ☰ | C33: Year Picker (Cover Page!C6) | D33: Dropdown of all 10 fiscal years; KPI tiles refresh via INDEX/MATCH.
B34: ☰ | C34: Year Picker (Summary!C4) | D34: Same dropdown driving the six KPI tiles on Summary.
B35: ☰ | C35: Compare Picker (Summary!F4) | D35: Pick a benchmark year; the delta row (B9:G9) shows green / red arrows.
B36: ☰ | C36: Hyperlinks | D36: Drill from Summary line items (Revenue, EBITDA, PAT, Total Assets, etc.) into source statements.
B37: ☰ | C37: Conditional data bars | D37: Revenue, EBITDA, PAT, CFO, EPS rows on Summary use brand-colored data bars.
B38: ☰ | C38: Charts | D38: Revenue & Profitability + Cash Flow Generation charts on Summary; Revenue Trajectory on Cover Page.
B40: 5 | C40: EDITING THE FORECAST
B42: ✎ | C42: Revenue growth | D42: Assumptions row 7 (annual % growth applied to product/service revenue lines).
B43: ✎ | C43: Cost ratios | D43: Assumptions rows 11-13 (COGS, employee costs, other expenses as % of revenue).
B44: ✎ | C44: Working capital | D44: Assumptions rows 18-20 (DSO, DIO, DPO in days).
B45: ✎ | C45: Capex & financing | D45: Assumptions rows 23-25 (capex, dividend payout, depreciation rate).
B46: ✎ | C46: Tax & other | D46: Assumptions rows 15, 27-30 (effective tax, finance cost rate, NCI %, etc.).
B48: 6 | C48: COLOR & FORMAT CONVENTIONS
B50: 1234.56 | D50: Hardcoded forecast input — manually entered assumption (yellow fill).
B51: 1234.56 | D51: Forecast formula — forward-looking calculation in violet text.
B52: SECTION | D52: Major section header (deep violet — Asian Paints brand primary).
B53: SUB-SEC | D53: Sub-section / table header (cinnabar — Asian Paints brand accent).
B54: 1234.56 | D54: Subtotal / Total row — bold with bottom border.
B55: 0 | D55: Balance check — must equal 0; red flag if non-zero.
B57: 7 | C57: VALIDATION & CAUTIONS
B59: ⚠ | C59: Balance Check | D59: Watch Balance Sheet row 65 — if non-zero, the model is out of balance.
B60: ⚠ | C60: Sign Conventions | D60: Capex and Dividends are stored as negative numbers in CF; positive in chart helper.
B61: ⚠ | C61: Cash Plug | D61: Cash position acts as the balancing plug; under-funded forecasts may show negative cash.
B62: ⚠ | C62: Helper Data | D62: Summary rows 71-86 power charts and deltas — do not edit or delete these rows.
B64: 8 | C64: NOTES & DISCLAIMER
D66: Source: Asian Paints Ltd. Annual Reports FY21-FY25; NSE/BSE filings; brokerage research; management commentary.
D67: Prepared as part of an independent academic / analytical exercise.
D68: Disclaimer: This valuation is for illustrative & educational purposes only. It does not constitute investment advice, recommendation, or solicitation.
D69: All figures are model outputs subject to assumptions; actual results may differ materially.

Sheet Assumptions
B1: Asian Paints Limited - Forecast Assumptions
B2: (₹ in Crores unless noted)
C3: Historical | I3: Forecast
B4: Particulars | C4: 31.03.2021 | D4: 31.03.2022 | E4: 31.03.2023 | F4: 31.03.2024 | G4: 31.03.2025 | I4: 31.03.2026E | J4: 31.03.2027E | K4: 31.03.2028E | L4: 31.03.2029E | M4: 31.03.2030E
B5: REVENUE & GROWTH
B6: Revenue from Operations | C6: ='Income Statement & Forecast'!C6+'Income Statement & Forecast'!C7+'Income Statement & Forecast'!C8 -> 21712.79 | D6: ='Income Statement & Forecast'!D6+'Income Statement & Forecast'!D7+'Income Statement & Forecast'!D8 -> 29101.28 | E6: ='Income Statement & Forecast'!E6+'Income Statement & Forecast'!E7+'Income Statement & Forecast'!E8 -> 34488.59 | F6: ='Income Statement & Forecast'!F6+'Income Statement & Forecast'!F7+'Income Statement & Forecast'!F8 -> 35494.73 | G6: ='Income Statement & Forecast'!G6+'Income Statement & Forecast'!G7+'Income Statement & Forecast'!G8 -> 33905.62 | I6: =G6*(1+I7) -> 35939.957 | J6: =I6*(1+J7) -> 38815.154 | K6: =J6*(1+K7) -> 41920.366 | L6: =K6*(1+L7) -> 45273.995 | M6: =L6*(1+M7) -> 48443.175
B7: Revenue Growth (%) | D7: =D6/C6-1 -> 0.34028285 | E7: =E6/D6-1 -> 0.18512278 | F7: =F6/E6-1 -> 0.029173127 | G7: =G6/F6-1 -> -0.044770308 | I7: 0.06 | J7: 0.08 | K7: 0.08 | L7: 0.08 | M7: 0.07
B8: Other Income | C8: ='Income Statement & Forecast'!C9 -> 303.05 | D8: ='Income Statement & Forecast'!D9 -> 380.01 | E8: ='Income Statement & Forecast'!E9 -> 386.48 | F8: ='Income Statement & Forecast'!F9 -> 687.96 | G8: ='Income Statement & Forecast'!G9 -> 572.61 | I8: 600 | J8: 650 | K8: 700 | L8: 750 | M8: 800
B10: COST DRIVERS
B11: COGS (% of Revenue) | C11: =('Income Statement & Forecast'!C12+'Income Statement & Forecast'!C13+'Income Statement & Forecast'!C14)/C6 -> 0.55714765 | D11: =('Income Statement & Forecast'!D12+'Income Statement & Forecast'!D13+'Income Statement & Forecast'!D14)/D6 -> 0.62886409 | E11: =('Income Statement & Forecast'!E12+'Income Statement & Forecast'!E13+'Income Statement & Forecast'!E14)/E6 -> 0.61343476 | F11: =('Income Statement & Forecast'!F12+'Income Statement & Forecast'!F13+'Income Statement & Forecast'!F14)/F6 -> 0.56600543 | G11: =('Income Statement & Forecast'!G12+'Income Statement & Forecast'!G13+'Income Statement & Forecast'!G14)/G6 -> 0.5755913 | I11: 0.59 | J11: 0.59 | K11: 0.59 | L11: 0.59 | M11: 0.59
B12: Employee Expense (% of Revenue) | C12: ='Income Statement & Forecast'!C15/C6 -> 0.07096048 | D12: ='Income Statement & Forecast'!D15/D6 -> 0.061394894 | E12: ='Income Statement & Forecast'!E15/E6 -> 0.058804086 | F12: ='Income Statement & Forecast'!F15/F6 -> 0.065535926 | G12: ='Income Statement & Forecast'!G15/G6 -> 0.076601755 | I12: 0.075 | J12: 0.075 | K12: 0.075 | L12: 0.075 | M12: 0.075
B13: Other Expenses (% of Revenue) | C13: ='Income Statement & Forecast'!C16/C6 -> 0.1482633 | D13: ='Income Statement & Forecast'!D16/D6 -> 0.14467577 | E13: ='Income Statement & Forecast'!E16/E6 -> 0.14625649 | F13: ='Income Statement & Forecast'!F16/F6 -> 0.15476551 | G13: ='Income Statement & Forecast'!G16/G6 -> 0.17066197 | I13: 0.16 | J13: 0.16 | K13: 0.16 | L13: 0.16 | M13: 0.16
B14: D&A Growth (%) | D14: ='Income Statement & Forecast'!D20/'Income Statement & Forecast'!C20-1 -> 0.031708519 | E14: ='Income Statement & Forecast'!E20/'Income Statement & Forecast'!D20-1 -> 0.051031408 | F14: ='Income Statement & Forecast'!F20/'Income Statement & Forecast'!E20-1 -> -0.0058506795 | G14: ='Income Statement & Forecast'!G20/'Income Statement & Forecast'!F20-1 -> 0.20321219 | I14: 0.08 | J14: 0.08 | K14: 0.08 | L14: 0.08 | M14: 0.08
B15: Effective Tax Rate (%) | C15: ='Income Statement & Forecast'!C30/'Income Statement & Forecast'!C25 -> 0.25499785 | D15: ='Income Statement & Forecast'!D30/'Income Statement & Forecast'!D25 -> 0.26336766 | E15: ='Income Statement & Forecast'!E30/'Income Statement & Forecast'!E25 -> 0.26253201 | F15: ='Income Statement & Forecast'!F30/'Income Statement & Forecast'!F25 -> 0.24362221 | G15: ='Income Statement & Forecast'!G30/'Income Statement & Forecast'!G25 -> 0.27304348 | I15: 0.26 | J15: 0.26 | K15: 0.26 | L15: 0.26 | M15: 0.26
B17: WORKING CAPITAL DAYS
B18: Days Sales Outstanding (DSO) | C18: ='Balance Sheet & Forecast'!C26/C$6*365 -> 43.743436 | D18: ='Balance Sheet & Forecast'!D26/D$6*365 -> 48.557163 | E18: ='Balance Sheet & Forecast'!E26/E$6*365 -> 49.073711 | F18: ='Balance Sheet & Forecast'!F26/F$6*365 -> 50.275161 | G18: ='Balance Sheet & Forecast'!G26/G$6*365 -> 46.437206 | I18: 50 | J18: 50 | K18: 50 | L18: 50 | M18: 50
B19: Days Inventory Outstanding (DIO) | C19: ='Balance Sheet & Forecast'!C23/(C$11*C$6)*365 -> 114.61211 | D19: ='Balance Sheet & Forecast'!D23/(D$11*D$6)*365 -> 122.71834 | E19: ='Balance Sheet & Forecast'!E23/(E$11*E$6)*365 -> 107.14833 | F19: ='Balance Sheet & Forecast'!F23/(F$11*F$6)*365 -> 107.61683 | G19: ='Balance Sheet & Forecast'!G23/(G$11*G$6)*365 -> 125.66926 | I19: 125 | J19: 125 | K19: 125 | L19: 125 | M19: 125
B20: Days Payables Outstanding (DPO) | C20: =('Balance Sheet & Forecast'!C56+'Balance Sheet & Forecast'!C57)/(C$11*C$6)*365 -> 101.9434 | D20: =('Balance Sheet & Forecast'!D56+'Balance Sheet & Forecast'!D57)/(D$11*D$6)*365 -> 83.055039 | E20: =('Balance Sheet & Forecast'!E56+'Balance Sheet & Forecast'!E57)/(E$11*E$6)*365 -> 62.719996 | F20: =('Balance Sheet & Forecast'!F56+'Balance Sheet & Forecast'!F57)/(F$11*F$6)*365 -> 69.607988 | G20: =('Balance Sheet & Forecast'!G56+'Balance Sheet & Forecast'!G57)/(G$11*G$6)*365 -> 71.968428 | I20: 70 | J20: 70 | K20: 70 | L20: 70 | M20: 70
B22: CAPEX & FINANCING
B23: Capex (% of Revenue) | C23: =-'Cash Flow Statement & Forecast'!C45/C$6 -> 0.012981749 | D23: =-'Cash Flow Statement & Forecast'!D45/D$6 -> 0.018495406 | E23: =-'Cash Flow Statement & Forecast'!E45/E$6 -> 0.036921486 | F23: =-'Cash Flow Statement & Forecast'!F45/F$6 -> 0.061953141 | G23: =-'Cash Flow Statement & Forecast'!G45/G$6 -> 0.05324545 | I23: 0.07 | J23: 0.07 | K23: 0.06 | L23: 0.06 | M23: 0.06
B24: Finance Costs (% of Revenue) | C24: ='Income Statement & Forecast'!C19/C$6 -> 0.0042200933 | D24: ='Income Statement & Forecast'!D19/D$6 -> 0.0032785499 | E24: ='Income Statement & Forecast'!E19/E$6 -> 0.0041883417 | F24: ='Income Statement & Forecast'!F19/F$6 -> 0.0057802947 | G24: ='Income Statement & Forecast'!G19/G$6 -> 0.0066956451 | I24: 0.0065 | J24: 0.0065 | K24: 0.0065 | L24: 0.0065 | M24: 0.0065
B25: Dividend Payout Ratio | C25: =-'Cash Flow Statement & Forecast'!C70/'Income Statement & Forecast'!C31 -> 0.15571841 | D25: =-'Cash Flow Statement & Forecast'!D70/'Income Statement & Forecast'!D31 -> 0.57144524 | E25: =-'Cash Flow Statement & Forecast'!E70/'Income Statement & Forecast'!E31 -> 0.4614774 | F25: =-'Cash Flow Statement & Forecast'!F70/'Income Statement & Forecast'!F31 -> 0.45898206 | G25: =-'Cash Flow Statement & Forecast'!G70/'Income Statement & Forecast'!G31 -> 0.84648396 | I25: 0.7 | J25: 0.7 | K25: 0.7 | L25: 0.7 | M25: 0.7
B27: OTHER ASSUMPTIONS
B28: Equity Shares Outstanding (Crores) | C28: ='Balance Sheet & Forecast'!C37 -> 95.92 | D28: ='Balance Sheet & Forecast'!D37 -> 95.92 | E28: ='Balance Sheet & Forecast'!E37 -> 95.92 | F28: ='Balance Sheet & Forecast'!F37 -> 95.92 | G28: ='Balance Sheet & Forecast'!G37 -> 95.92 | I28: =G28 -> 95.92 | J28: =I28 -> 95.92 | K28: =J28 -> 95.92 | L28: =K28 -> 95.92 | M28: =L28 -> 95.92
B29: Share of Profit in Associates Growth | D29: ='Income Statement & Forecast'!D22/'Income Statement & Forecast'!C22-1 -> 0.10384615 | E29: ='Income Statement & Forecast'!E22/'Income Statement & Forecast'!D22-1 -> 1.9727589 | F29: ='Income Statement & Forecast'!F22/'Income Statement & Forecast'!E22-1 -> 0.41715503 | G29: ='Income Statement & Forecast'!G22/'Income Statement & Forecast'!F22-1 -> 0.057969925 | I29: 0.05 | J29: 0.05 | K29: 0.05 | L29: 0.05 | M29: 0.05
B30: NCI Share of PAT (%) | C30: ='Income Statement & Forecast'!C36/'Income Statement & Forecast'!C31 -> 0.021036875 | D30: ='Income Statement & Forecast'!D36/'Income Statement & Forecast'!D31 -> 0.017582931 | E30: ='Income Statement & Forecast'!E36/'Income Statement & Forecast'!E31 -> 0.021185461 | F30: ='Income Statement & Forecast'!F36/'Income Statement & Forecast'!F31 -> 0.017536063 | G30: ='Income Statement & Forecast'!G36/'Income Statement & Forecast'!G31 -> 0.01145103 | I30: 0.0115 | J30: 0.0115 | K30: 0.0115 | L30: 0.0115 | M30: 0.0115

Sheet Balance Sheet & Forecast
B1: Asian Paints Limited - Consolidated Balance Sheet
B2: (₹ in Crores)
C3: As at | I3: Forecast
B4: Particulars | C4: 31.03.2021 | D4: 31.03.2022 | E4: 31.03.2023 | F4: 31.03.2024 | G4: 31.03.2025 | I4: 31.03.2026E | J4: 31.03.2027E | K4: 31.03.2028E | L4: 31.03.2029E | M4: 31.03.2030E
B5: ASSETS
B6: Non-Current Assets
B7: Property, Plant and Equipment | C7: 4476.35 | D7: 4184.46 | E7: 4145.65 | F7: 4446.2 | G7: 6787.62 | I7: =G7+Assumptions!I23*(Assumptions!I6)-'Income Statement & Forecast'!I20 -> 8194.9698 | J7: =I7+Assumptions!J23*(Assumptions!J6)-'Income Statement & Forecast'!J20 -> 9714.9076 | K7: =J7+Assumptions!K23*(Assumptions!K6)-'Income Statement & Forecast'!K20 -> 10937.237 | L7: =K7+Assumptions!L23*(Assumptions!L6)-'Income Statement & Forecast'!L20 -> 12257.352 | M7: =L7+Assumptions!M23*(Assumptions!M6)-'Income Statement & Forecast'!M20 -> 13655.913
B8: Right-of-Use Assets | C8: 845.55 | D8: 905.75 | E8: 1208.92 | F8: 1856.27 | G8: 1843.72 | I8: =G8 -> 1843.72 | J8: =I8 -> 1843.72 | K8: =J8 -> 1843.72 | L8: =K8 -> 1843.72 | M8: =L8 -> 1843.72
B9: Capital work-in-progress | C9: 182.98 | D9: 426.43 | E9: 1019.59 | F9: 2698.37 | G9: 1254.49 | I9: =G9 -> 1254.49 | J9: =I9 -> 1254.49 | K9: =J9 -> 1254.49 | L9: =K9 -> 1254.49 | M9: =L9 -> 1254.49
B10: Goodwill | C10: 302.63 | D10: 242.86 | E10: 228.48 | F10: 419.19 | G10: 219.58 | I10: =G10 -> 219.58 | J10: =I10 -> 219.58 | K10: =J10 -> 219.58 | L10: =K10 -> 219.58 | M10: =L10 -> 219.58
B11: Other Intangible Assets | C11: 233.99 | D11: 185.99 | E11: 187.41 | F11: 424.96 | G11: 369.18 | I11: =G11 -> 369.18 | J11: =I11 -> 369.18 | K11: =J11 -> 369.18 | L11: =K11 -> 369.18 | M11: =L11 -> 369.18
B12: Investments in Associates | C12: 483.9 | D12: 515.47 | E12: 781.73 | F12: 583.13 | G12: 608 | I12: =G12+'Income Statement & Forecast'!I22 -> 755.7455 | J12: =I12+'Income Statement & Forecast'!J22 -> 910.87828 | K12: =J12+'Income Statement & Forecast'!K22 -> 1073.7677 | L12: =K12+'Income Statement & Forecast'!L22 -> 1244.8016 | M12: =L12+'Income Statement & Forecast'!M22 -> 1424.3872
B13: Financial Assets
B14: Investments | C14: 985.78 | D14: 551.36 | E14: 782.98 | F14: 801.38 | G14: 871.79 | I14: =G14 -> 871.79 | J14: =I14 -> 871.79 | K14: =J14 -> 871.79 | L14: =K14 -> 871.79 | M14: =L14 -> 871.79
B15: Trade Receivables | C15: 2.89 | D15: 2.4 | E15: 2.17 | F15: 1.78 | G15: 8.71 | I15: =G15 -> 8.71 | J15: =I15 -> 8.71 | K15: =J15 -> 8.71 | L15: =K15 -> 8.71 | M15: =L15 -> 8.71
B16: Loans | C16: 61.89 | I16: =G16 -> 0 | J16: =I16 -> 0 | K16: =J16 -> 0 | L16: =K16 -> 0 | M16: =L16 -> 0
B17: Other Financial Assets | C17: 532.17 | D17: 486.05 | E17: 363.18 | F17: 606.51 | G17: 877.84 | I17: =G17 -> 877.84 | J17: =I17 -> 877.84 | K17: =J17 -> 877.84 | L17: =K17 -> 877.84 | M17: =L17 -> 877.84
B18: Deferred Tax Assets (Net) | C18: 14.28 | D18: 26.02 | E18: 18.67 | F18: 23.32 | G18: 16.12 | I18: =G18 -> 16.12 | J18: =I18 -> 16.12 | K18: =J18 -> 16.12 | L18: =K18 -> 16.12 | M18: =L18 -> 16.12
B19: Income Tax Assets (Net) | C19: 152.23 | D19: 172.46 | E19: 189.52 | F19: 198.11 | G19: 221.62 | I19: =G19 -> 221.62 | J19: =I19 -> 221.62 | K19: =J19 -> 221.62 | L19: =K19 -> 221.62 | M19: =L19 -> 221.62
B20: Other Non-Current Assets | C20: 68.38 | D20: 132.87 | E20: 334.54 | F20: 327.81 | G20: 301.02 | I20: =G20 -> 301.02 | J20: =I20 -> 301.02 | K20: =J20 -> 301.02 | L20: =K20 -> 301.02 | M20: =L20 -> 301.02
B21: Total Non-Current Assets | C21: 8343.02 | D21: 7832.12 | E21: 9262.84 | F21: 12387.03 | G21: 13379.69 | I21: =SUM(I7:I12)+SUM(I14:I20) -> 14934.785 | J21: =SUM(J7:J12)+SUM(J14:J20) -> 16609.856 | K21: =SUM(K7:K12)+SUM(K14:K20) -> 17995.074 | L21: =SUM(L7:L12)+SUM(L14:L20) -> 19486.224 | M21: =SUM(M7:M12)+SUM(M14:M20) -> 21064.37
B22: Current Assets
B23: Inventories | C23: 3798.6 | D23: 6152.98 | E23: 6210.64 | F23: 5923.41 | G23: 6719.27 | I23: =Assumptions!I19*(Assumptions!I11*(Assumptions!I6+'Income Statement & Forecast'!I7+'Income Statement & Forecast'!I8))/365 -> 7321.5535 | J23: =Assumptions!J19*(Assumptions!J11*(Assumptions!J6+'Income Statement & Forecast'!J7+'Income Statement & Forecast'!J8))/365 -> 7907.2778 | K23: =Assumptions!K19*(Assumptions!K11*(Assumptions!K6+'Income Statement & Forecast'!K7+'Income Statement & Forecast'!K8))/365 -> 8539.86 | L23: =Assumptions!L19*(Assumptions!L11*(Assumptions!L6+'Income Statement & Forecast'!L7+'Income Statement & Forecast'!L8))/365 -> 9223.0488 | M23: =Assumptions!M19*(Assumptions!M11*(Assumptions!M6+'Income Statement & Forecast'!M7+'Income Statement & Forecast'!M8))/365 -> 9868.6622
B24: Financial Assets
B25: Investments | C25: 3267.12 | D25: 2180.7 | E25: 2697 | F25: 3203.41 | G25: 3244.96 | I25: =G25 -> 3244.96 | J25: =I25 -> 3244.96 | K25: =J25 -> 3244.96 | L25: =K25 -> 3244.96 | M25: =L25 -> 3244.96
B26: Trade Receivables | C26: 2602.17 | D26: 3871.44 | E26: 4636.94 | F26: 4889.05 | G26: 4313.65 | I26: =Assumptions!I18*(Assumptions!I6+'Income Statement & Forecast'!I7+'Income Statement & Forecast'!I8)/365 -> 4963.7651 | J26: =Assumptions!J18*(Assumptions!J6+'Income Statement & Forecast'!J7+'Income Statement & Forecast'!J8)/365 -> 5360.8663 | K26: =Assumptions!K18*(Assumptions!K6+'Income Statement & Forecast'!K7+'Income Statement & Forecast'!K8)/365 -> 5789.7356 | L26: =Assumptions!L18*(Assumptions!L6+'Income Statement & Forecast'!L7+'Income Statement & Forecast'!L8)/365 -> 6252.9145 | M26: =Assumptions!M18*(Assumptions!M6+'Income Statement & Forecast'!M7+'Income Statement & Forecast'!M8)/365 -> 6690.6185
B27: Cash and Cash Equivalents | C27: 346.39 | D27: 621.72 | E27: 523.1 | F27: 829.34 | G27: 445.28 | I27: =G27+'Cash Flow Statement & Forecast'!I73 -> -845.81375 | J27: =I27+'Cash Flow Statement & Forecast'!J73 -> -1810.7676 | K27: =J27+'Cash Flow Statement & Forecast'!K73 -> -2430.5372 | L27: =K27+'Cash Flow Statement & Forecast'!L73 -> -3097.4186 | M27: =L27+'Cash Flow Statement & Forecast'!M73 -> -3702.5393
B28: Other Balances with Banks | C28: 264.36 | D28: 242.61 | E28: 320.72 | F28: 254.67 | G28: 336.7 | I28: =G28 -> 336.7 | J28: =I28 -> 336.7 | K28: =J28 -> 336.7 | L28: =K28 -> 336.7 | M28: =L28 -> 336.7
B29: Loans | C29: 17.59 | I29: =G29 -> 0 | J29: =I29 -> 0 | K29: =J29 -> 0 | L29: =K29 -> 0 | M29: =L29 -> 0
B30: Other Financial Assets | C30: 1179.65 | D30: 1533.5 | E30: 1592.78 | F30: 1651.35 | G30: 1158.11 | I30: =G30 -> 1158.11 | J30: =I30 -> 1158.11 | K30: =J30 -> 1158.11 | L30: =K30 -> 1158.11 | M30: =L30 -> 1158.11
B31: Other Current Assets | C31: 537.23 | D31: 541.25 | E31: 553.98 | F31: 785.83 | G31: 773.71 | I31: =G31 -> 773.71 | J31: =I31 -> 773.71 | K31: =J31 -> 773.71 | L31: =K31 -> 773.71 | M31: =L31 -> 773.71
B32: Assets classified as Held for Sale | C32: 13.49 | D32: 8.13 | E32: 0 | I32: =G32 -> 0 | J32: =I32 -> 0 | K32: =J32 -> 0 | L32: =K32 -> 0 | M32: =L32 -> 0
B33: Total Current Assets | C33: 12026.6 | D33: 15152.33 | E33: 16535.16 | F33: 17537.06 | G33: 16991.68 | I33: =SUM(I23:I32) -> 16952.985 | J33: =SUM(J23:J32) -> 16970.857 | K33: =SUM(K23:K32) -> 17412.538 | L33: =SUM(L23:L32) -> 17892.025 | M33: =SUM(M23:M32) -> 18370.221
B34: TOTAL ASSETS | C34: 20369.62 | D34: 22984.45 | E34: 25798 | F34: 29924.09 | G34: 30371.37 | I34: =I21+I33 -> 31887.77 | J34: =J21+J33 -> 33580.712 | K34: =K21+K33 -> 35407.613 | L34: =L21+L33 -> 37378.248 | M34: =M21+M33 -> 39434.591
B35: EQUITY AND LIABILITIES
B36: Equity
B37: Equity Share Capital | C37: 95.92 | D37: 95.92 | E37: 95.92 | F37: 95.92 | G37: 95.92 | I37: =G37 -> 95.92 | J37: =I37 -> 95.92 | K37: =J37 -> 95.92 | L37: =K37 -> 95.92 | M37: =L37 -> 95.92
B38: Other Equity | C38: 12710.37 | D38: 13715.64 | E38: 15896.31 | F38: 18632.38 | G38: 19303.89 | I38: =G38+'Income Statement & Forecast'!I35-(Assumptions!I25*'Income Statement & Forecast'!I35) -> 20553.68 | J38: =I38+'Income Statement & Forecast'!J35-(Assumptions!J25*'Income Statement & Forecast'!J35) -> 21902.92 | K38: =J38+'Income Statement & Forecast'!K35-(Assumptions!K25*'Income Statement & Forecast'!K35) -> 23358.639 | L38: =K38+'Income Statement & Forecast'!L35-(Assumptions!L25*'Income Statement & Forecast'!L35) -> 24928.426 | M38: =L38+'Income Statement & Forecast'!M35-(Assumptions!M25*'Income Statement & Forecast'!M35) -> 26603.735
B39: Equity attributable to owners of the Company | C39: 12806.29 | D39: 13811.56 | E39: 15992.23 | F39: 18728.3 | G39: 19399.81 | I39: =I37+I38 -> 20649.6 | J39: =J37+J38 -> 21998.84 | K39: =K37+K38 -> 23454.559 | L39: =L37+L38 -> 25024.346 | M39: =M37+M38 -> 26699.655
B40: Non-Controlling Interests | C40: 422.86 | D40: 387.53 | E40: 453.66 | F40: 695.38 | G40: 659.24 | I40: =G40+'Income Statement & Forecast'!I36-(Assumptions!I25*'Income Statement & Forecast'!I36) -> 673.7798 | J40: =I40+'Income Statement & Forecast'!J36-(Assumptions!J25*'Income Statement & Forecast'!J36) -> 689.47657 | K40: =J40+'Income Statement & Forecast'!K36-(Assumptions!K25*'Income Statement & Forecast'!K36) -> 706.41209 | L40: =K40+'Income Statement & Forecast'!L36-(Assumptions!L25*'Income Statement & Forecast'!L36) -> 724.67467 | M40: =L40+'Income Statement & Forecast'!M36-(Assumptions!M25*'Income Statement & Forecast'!M36) -> 744.16486
B41: Total Equity | C41: 13229.15 | D41: 14199.09 | E41: 16445.89 | F41: 19423.68 | G41: 20059.05 | I41: =I39+I40 -> 21323.38 | J41: =J39+J40 -> 22688.317 | K41: =K39+K40 -> 24160.971 | L41: =L39+L40 -> 25749.021 | M41: =M39+M40 -> 27443.82
B42: Non-Current Liabilities
B43: Financial Liabilities
B44: Borrowings | C44: 14.53 | D44: 44.54 | E44: 76.15 | F44: 54.38 | G44: 259.62 | I44: =G44 -> 259.62 | J44: =I44 -> 259.62 | K44: =J44 -> 259.62 | L44: =K44 -> 259.62 | M44: =L44 -> 259.62
B45: Lease Liabilities | C45: 561.36 | D45: 598.37 | E45: 728.94 | F45: 1095.29 | G45: 1123.3 | I45: =G45 -> 1123.3 | J45: =I45 -> 1123.3 | K45: =J45 -> 1123.3 | L45: =K45 -> 1123.3 | M45: =L45 -> 1123.3
B46: Other Financial Liabilities | C46: 3.38 | D46: 2.18 | E46: 46.38 | F46: 240.58 | G46: 79.93 | I46: =G46 -> 79.93 | J46: =I46 -> 79.93 | K46: =J46 -> 79.93 | L46: =K46 -> 79.93 | M46: =L46 -> 79.93
B47: Provisions | C47: 215.21 | D47: 218.32 | E47: 230.7 | F47: 222.56 | G47: 257.78 | I47: =G47 -> 257.78 | J47: =I47 -> 257.78 | K47: =J47 -> 257.78 | L47: =K47 -> 257.78 | M47: =L47 -> 257.78
B48: Deferred Tax Liabilities (Net) | C48: 415.59 | D48: 348.85 | E48: 334.84 | F48: 352.17 | G48: 404.91 | I48: =G48 -> 404.91 | J48: =I48 -> 404.91 | K48: =J48 -> 404.91 | L48: =K48 -> 404.91 | M48: =L48 -> 404.91
B49: Other Non-Current Liabilities | C49: 4.54 | D49: 2.11 | E49: 39.17 | F49: 34.47 | G49: 45.55 | I49: =G49 -> 45.55 | J49: =I49 -> 45.55 | K49: =J49 -> 45.55 | L49: =K49 -> 45.55 | M49: =L49 -> 45.55
B50: Total Non-Current Liabilities | C50: 1214.61 | D50: 1214.37 | E50: 1456.18 | F50: 1999.45 | G50: 2171.09 | I50: =SUM(I44:I49) -> 2171.09 | J50: =SUM(J44:J49) -> 2171.09 | K50: =SUM(K44:K49) -> 2171.09 | L50: =SUM(L44:L49) -> 2171.09 | M50: =SUM(M44:M49) -> 2171.09
B51: Current Liabilities
B52: Financial Liabilities
B53: Borrowings | C53: 325.7 | D53: 731.12 | E53: 896.06 | F53: 1052.76 | G53: 604.13 | I53: =G53 -> 604.13 | J53: =I53 -> 604.13 | K53: =J53 -> 604.13 | L53: =K53 -> 604.13 | M53: =L53 -> 604.13
B54: Lease Liabilities | C54: 183.18 | D54: 212.85 | E54: 231.47 | F54: 271.95 | G54: 303.24 | I54: =G54 -> 303.24 | J54: =I54 -> 303.24 | K54: =J54 -> 303.24 | L54: =K54 -> 303.24 | M54: =L54 -> 303.24
B55: Trade Payables
B56: Total Outstanding dues of Micro Enterprises and Small Enterprises | C56: 91.53 | D56: 83.58 | E56: 143.88 | F56: 250.27 | G56: 208.58 | I56: =Assumptions!I20*(Assumptions!I11*(Assumptions!I6+'Income Statement & Forecast'!I7+'Income Statement & Forecast'!I8))/365*(G56/(G56+G57)) -> 222.2434 | J56: =Assumptions!J20*(Assumptions!J11*(Assumptions!J6+'Income Statement & Forecast'!J7+'Income Statement & Forecast'!J8))/365*(I56/(I56+I57)) -> 240.02287 | K56: =Assumptions!K20*(Assumptions!K11*(Assumptions!K6+'Income Statement & Forecast'!K7+'Income Statement & Forecast'!K8))/365*(J56/(J56+J57)) -> 259.2247 | L56: =Assumptions!L20*(Assumptions!L11*(Assumptions!L6+'Income Statement & Forecast'!L7+'Income Statement & Forecast'!L8))/365*(K56/(K56+K57)) -> 279.96267 | M56: =Assumptions!M20*(Assumptions!M11*(Assumptions!M6+'Income Statement & Forecast'!M7+'Income Statement & Forecast'!M8))/365*(L56/(L56+L57)) -> 299.56006
B57: Total Outstanding dues of Creditors other than Micro Enterprises and Small Enterprises | C57: 3287.19 | D57: 4080.72 | E57: 3491.56 | F57: 3581.07 | G57: 3639.42 | I57: =Assumptions!I20*(Assumptions!I11*(Assumptions!I6+'Income Statement & Forecast'!I7+'Income Statement & Forecast'!I8))/365*(G57/(G56+G57)) -> 3877.8266 | J57: =Assumptions!J20*(Assumptions!J11*(Assumptions!J6+'Income Statement & Forecast'!J7+'Income Statement & Forecast'!J8))/365*(I57/(I56+I57)) -> 4188.0527 | K57: =Assumptions!K20*(Assumptions!K11*(Assumptions!K6+'Income Statement & Forecast'!K7+'Income Statement & Forecast'!K8))/365*(J57/(J56+J57)) -> 4523.0969 | L57: =Assumptions!L20*(Assumptions!L11*(Assumptions!L6+'Income Statement & Forecast'!L7+'Income Statement & Forecast'!L8))/365*(K57/(K56+K57)) -> 4884.9447 | M57: =Assumptions!M20*(Assumptions!M11*(Assumptions!M6+'Income Statement & Forecast'!M7+'Income Statement & Forecast'!M8))/365*(L57/(L56+L57)) -> 5226.8908
B58: Other Financial Liabilities | C58: 1603.02 | D58: 1886.81 | E58: 2436.02 | F58: 2675.44 | G58: 2742.04 | I58: =G58 -> 2742.04 | J58: =I58 -> 2742.04 | K58: =J58 -> 2742.04 | L58: =K58 -> 2742.04 | M58: =L58 -> 2742.04
B59: Other Current Liabilities | C59: 229.58 | D59: 376.09 | E59: 459.04 | F59: 484.48 | G59: 450.58 | I59: =G59 -> 450.58 | J59: =I59 -> 450.58 | K59: =J59 -> 450.58 | L59: =K59 -> 450.58 | M59: =L59 -> 450.58
B60: Provisions | C60: 84.43 | D60: 69.7 | E60: 74.21 | F60: 62.48 | G60: 67.15 | I60: =G60 -> 67.15 | J60: =I60 -> 67.15 | K60: =J60 -> 67.15 | L60: =K60 -> 67.15 | M60: =L60 -> 67.15
B61: Income Tax Liabilities (Net) | C61: 121.23 | D61: 130.12 | E61: 163.69 | F61: 122.51 | G61: 126.09 | I61: =G61 -> 126.09 | J61: =I61 -> 126.09 | K61: =J61 -> 126.09 | L61: =K61 -> 126.09 | M61: =L61 -> 126.09
B62: Total Current Liabilities | C62: 5925.86 | D62: 7570.99 | E62: 7895.93 | F62: 8500.96 | G62: 8141.23 | I62: =SUM(I53:I54)+SUM(I56:I61) -> 8393.3 | J62: =SUM(J53:J54)+SUM(J56:J61) -> 8721.3056 | K62: =SUM(K53:K54)+SUM(K56:K61) -> 9075.5516 | L62: =SUM(L53:L54)+SUM(L56:L61) -> 9458.1373 | M62: =SUM(M53:M54)+SUM(M56:M61) -> 9819.6809
B63: TOTAL EQUITY AND LIABILITIES | C63: 20369.62 | D63: 22984.45 | E63: 25798 | F63: 29924.09 | G63: 30371.37 | I63: =I41+I50+I62 -> 31887.77 | J63: =J41+J50+J62 -> 33580.712 | K63: =K41+K50+K62 -> 35407.613 | L63: =L41+L50+L62 -> 37378.248 | M63: =M41+M50+M62 -> 39434.591
B65: Balance Check (TA - TE&L) | C65: =ROUND(C34-C63,2) -> 0 | D65: =ROUND(D34-D63,2) -> 0 | E65: =ROUND(E34-E63,2) -> 0 | F65: =ROUND(F34-F63,2) -> 0 | G65: =ROUND(G34-G63,2) -> 0 | I65: =ROUND(I34-I63,2) -> 0 | J65: =ROUND(J34-J63,2) -> 0 | K65: =ROUND(K34-K63,2) -> 0 | L65: =ROUND(L34-L63,2) -> 0 | M65: =ROUND(M34-M63,2) -> 0

Sheet Income Statement & Forecast
B1: Asian Paints Limited - Consolidated Statement of Profit and Loss
B2: (₹ in Crores)
C3: Year ended | I3: Forecast
B4: Particulars | C4: 31.03.2021 | D4: 31.03.2022 | E4: 31.03.2023 | F4: 31.03.2024 | G4: 31.03.2025 | I4: 31.03.2026E | J4: 31.03.2027E | K4: 31.03.2028E | L4: 31.03.2029E | M4: 31.03.2030E
B5: REVENUE FROM OPERATIONS
B6: Revenue from Sale of Products | C6: 21440.24 | D6: 28830.02 | E6: 34253.35 | F6: 35248.88 | G6: 33626.82 | I6: =G6*(1+Assumptions!I7) -> 35644.429 | J6: =I6*(1+Assumptions!J7) -> 38495.984 | K6: =J6*(1+Assumptions!K7) -> 41575.662 | L6: =K6*(1+Assumptions!L7) -> 44901.715 | M6: =L6*(1+Assumptions!M7) -> 48044.835
B7: Revenue from Sale of Services | C7: 44.96 | D7: 93.46 | E7: 114.48 | F7: 133.24 | G7: 170.54 | I7: =G7*(1+Assumptions!I7) -> 180.7724 | J7: =I7*(1+Assumptions!J7) -> 195.23419 | K7: =J7*(1+Assumptions!K7) -> 210.85293 | L7: =K7*(1+Assumptions!L7) -> 227.72116 | M7: =L7*(1+Assumptions!M7) -> 243.66164
B8: Other Operating Revenue | C8: 227.59 | D8: 177.8 | E8: 120.76 | F8: 112.61 | G8: 108.26 | I8: =G8*(1+Assumptions!I7) -> 114.7556 | J8: =I8*(1+Assumptions!J7) -> 123.93605 | K8: =J8*(1+Assumptions!K7) -> 133.85093 | L8: =K8*(1+Assumptions!L7) -> 144.55901 | M8: =L8*(1+Assumptions!M7) -> 154.67814
B9: Other Income | C9: 303.05 | D9: 380.01 | E9: 386.48 | F9: 687.96 | G9: 572.61 | I9: =Assumptions!I8 -> 600 | J9: =Assumptions!J8 -> 650 | K9: =Assumptions!K8 -> 700 | L9: =Assumptions!L8 -> 750 | M9: =Assumptions!M8 -> 800
B10: Total Income (I) | C10: 22015.84 | D10: 29481.29 | E10: 34875.07 | F10: 36182.69 | G10: 34478.23 | I10: =SUM(I6:I9) -> 36539.957 | J10: =SUM(J6:J9) -> 39465.154 | K10: =SUM(K6:K9) -> 42620.366 | L10: =SUM(L6:L9) -> 46023.995 | M10: =SUM(M6:M9) -> 49243.175
B11: EXPENSES
B12: Cost of Materials Consumed | C12: 10317.09 | D12: 16254.59 | E12: 17330.58 | F12: 15868.21 | G12: 15793.92 | I12: =Assumptions!I$11*(I$6+I$7+I$8)*($C12/($C$12+$C$13+$C$14)) -> 18084.264 | J12: =Assumptions!J$11*(J$6+J$7+J$8)*($C12/($C$12+$C$13+$C$14)) -> 19531.006 | K12: =Assumptions!K$11*(K$6+K$7+K$8)*($C12/($C$12+$C$13+$C$14)) -> 21093.486 | L12: =Assumptions!L$11*(L$6+L$7+L$8)*($C12/($C$12+$C$13+$C$14)) -> 22780.965 | M12: =Assumptions!M$11*(M$6+M$7+M$8)*($C12/($C$12+$C$13+$C$14)) -> 24375.632
B13: Purchases of Stock-in-Trade | C13: 1872.59 | D13: 3371.13 | E13: 4135.65 | F13: 3858.2 | G13: 3926.86 | I13: =Assumptions!I$11*(I$6+I$7+I$8)*($C13/($C$12+$C$13+$C$14)) -> 3282.3609 | J13: =Assumptions!J$11*(J$6+J$7+J$8)*($C13/($C$12+$C$13+$C$14)) -> 3544.9498 | K13: =Assumptions!K$11*(K$6+K$7+K$8)*($C13/($C$12+$C$13+$C$14)) -> 3828.5457 | L13: =Assumptions!L$11*(L$6+L$7+L$8)*($C13/($C$12+$C$13+$C$14)) -> 4134.8294 | M13: =Assumptions!M$11*(M$6+M$7+M$8)*($C13/($C$12+$C$13+$C$14)) -> 4424.2675
B14: Changes in inventories of finished goods, Stock-in-Trade and Work-in-Progress | C14: -92.45 | D14: -1324.97 | E14: -309.73 | F14: 363.8 | G14: -205 | I14: =Assumptions!I$11*(I$6+I$7+I$8)*($C14/($C$12+$C$13+$C$14)) -> -162.05056 | J14: =Assumptions!J$11*(J$6+J$7+J$8)*($C14/($C$12+$C$13+$C$14)) -> -175.01461 | K14: =Assumptions!K$11*(K$6+K$7+K$8)*($C14/($C$12+$C$13+$C$14)) -> -189.01578 | L14: =Assumptions!L$11*(L$6+L$7+L$8)*($C14/($C$12+$C$13+$C$14)) -> -204.13704 | M14: =Assumptions!M$11*(M$6+M$7+M$8)*($C14/($C$12+$C$13+$C$14)) -> -218.42663
B15: Employee Benefits Expense | C15: 1540.75 | D15: 1786.67 | E15: 2028.07 | F15: 2326.18 | G15: 2597.23 | I15: =Assumptions!I12*(I$6+I$7+I$8) -> 2695.4968 | J15: =Assumptions!J12*(J$6+J$7+J$8) -> 2911.1365 | K15: =Assumptions!K12*(K$6+K$7+K$8) -> 3144.0275 | L15: =Assumptions!L12*(L$6+L$7+L$8) -> 3395.5497 | M15: =Assumptions!M12*(M$6+M$7+M$8) -> 3633.2381
B16: Other Expenses | C16: 3219.21 | D16: 4210.25 | E16: 5044.18 | F16: 5493.36 | G16: 5786.4 | I16: =Assumptions!I13*(I$6+I$7+I$8) -> 5750.3932 | J16: =Assumptions!J13*(J$6+J$7+J$8) -> 6210.4246 | K16: =Assumptions!K13*(K$6+K$7+K$8) -> 6707.2586 | L16: =Assumptions!L13*(L$6+L$7+L$8) -> 7243.8393 | M16: =Assumptions!M13*(M$6+M$7+M$8) -> 7750.908
B17: Total Expenses (II) | C17: 16857.19 | D17: 24297.67 | E17: 28228.75 | F17: 27909.75 | G17: 27899.41 | I17: =SUM(I12:I16) -> 29650.465 | J17: =SUM(J12:J16) -> 32022.502 | K17: =SUM(K12:K16) -> 34584.302 | L17: =SUM(L12:L16) -> 37351.046 | M17: =SUM(M12:M16) -> 39965.619
B18: EARNING BEFORE INTEREST, TAX, DEPRECIATION AND AMORTISATION (EBITDA) (I-II) | C18: 5158.65 | D18: 5183.62 | E18: 6646.32 | F18: 8272.94 | G18: 6578.82 | I18: =I10-I17 -> 6889.4925 | J18: =J10-J17 -> 7442.6519 | K18: =K10-K17 -> 8036.0641 | L18: =L10-L17 -> 8672.9492 | M18: =M10-M17 -> 9277.5556
B19: Finance Costs | C19: 91.63 | D19: 95.41 | E19: 144.45 | F19: 205.17 | G19: 227.02 | I19: =Assumptions!I24*(I$6+I$7+I$8) -> 233.60972 | J19: =Assumptions!J24*(J$6+J$7+J$8) -> 252.2985 | K19: =Assumptions!K24*(K$6+K$7+K$8) -> 272.48238 | L19: =Assumptions!L24*(L$6+L$7+L$8) -> 294.28097 | M19: =Assumptions!M24*(M$6+M$7+M$8) -> 314.88064
B20: Depreciation and Amortisation Expense | C20: 791.27 | D20: 816.36 | E20: 858.02 | F20: 853 | G20: 1026.34 | I20: =G20*(1+Assumptions!I14) -> 1108.4472 | J20: =I20*(1+Assumptions!J14) -> 1197.123 | K20: =J20*(1+Assumptions!K14) -> 1292.8928 | L20: =K20*(1+Assumptions!L14) -> 1396.3242 | M20: =L20*(1+Assumptions!M14) -> 1508.0302
B21: PROFIT BEFORE SHARE OF PROFIT IN ASSOCIATES AND EXCEPTIONAL ITEMS | C21: 4275.75 | D21: 4271.85 | E21: 5643.85 | F21: 7214.77 | G21: 5325.46 | I21: =I18-I19-I20 -> 5547.4356 | J21: =J18-J19-J20 -> 5993.2304 | K21: =K18-K19-K20 -> 6470.6889 | L21: =L18-L19-L20 -> 6982.344 | M21: =M18-M19-M20 -> 7454.6448
B22: Share of profit in Associates | C22: 28.6 | D22: 31.57 | E22: 93.85 | F22: 133 | G22: 140.71 | I22: =G22*(1+Assumptions!I29) -> 147.7455 | J22: =I22*(1+Assumptions!J29) -> 155.13278 | K22: =J22*(1+Assumptions!K29) -> 162.88941 | L22: =K22*(1+Assumptions!L29) -> 171.03388 | M22: =L22*(1+Assumptions!M29) -> 179.58558
B23: PROFIT BEFORE EXCEPTIONAL ITEMS AND TAX | D23: 4303.42 | E23: 5737.7 | F23: 7347.77 | G23: 5466.17 | I23: =I21+I22 -> 5695.1811 | J23: =J21+J22 -> 6148.3632 | K23: =K21+K22 -> 6633.5783 | L23: =L21+L22 -> 7153.3779 | M23: =M21+M22 -> 7634.2304
B24: Exceptional Items | D24: 115.7 | E24: 48.87 | F24: 0 | G24: 363.1 | I24: 0 | J24: 0 | K24: 0 | L24: 0 | M24: 0
B25: PROFIT BEFORE TAX | C25: 4304.35 | D25: 4187.72 | E25: 5688.83 | F25: 7347.77 | G25: 5103.07 | I25: =I23-I24 -> 5695.1811 | J25: =J23-J24 -> 6148.3632 | K25: =K23-K24 -> 6633.5783 | L25: =L23-L24 -> 7153.3779 | M25: =M23-M24 -> 7634.2304
B26: Tax Expense
B27: Current Tax | C27: 1114.02 | D27: 1161.53 | E27: 1504.14 | F27: 1836 | G27: 1388.98 | I27: =Assumptions!I15*I25 -> 1480.7471 | J27: =Assumptions!J15*J25 -> 1598.5744 | K27: =Assumptions!K15*K25 -> 1724.7304 | L27: =Assumptions!L15*L25 -> 1859.8782 | M27: =Assumptions!M15*M25 -> 1984.8999
B28: Short tax provision for earlier years | C28: 7.74 | D28: 2.82 | E28: 6.64 | F28: -51.35 | G28: -13.39 | I28: 0 | J28: 0 | K28: 0 | L28: 0 | M28: 0
B29: Deferred Tax | C29: -24.16 | D29: -61.44 | E29: -17.28 | F29: 5.43 | G29: 17.77 | I29: 0 | J29: 0 | K29: 0 | L29: 0 | M29: 0
B30: Total tax expense | C30: 1097.6 | D30: 1102.91 | E30: 1493.5 | F30: 1790.08 | G30: 1393.36 | I30: =SUM(I27:I29) -> 1480.7471 | J30: =SUM(J27:J29) -> 1598.5744 | K30: =SUM(K27:K29) -> 1724.7304 | L30: =SUM(L27:L29) -> 1859.8782 | M30: =SUM(M27:M29) -> 1984.8999
B31: PROFIT AFTER TAX | C31: 3206.75 | D31: 3084.81 | E31: 4195.33 | F31: 5557.69 | G31: 3709.71 | I31: =I25-I30 -> 4214.434 | J31: =J25-J30 -> 4549.7888 | K31: =K25-K30 -> 4908.8479 | L31: =L25-L30 -> 5293.4996 | M31: =M25-M30 -> 5649.3305
B32: Total Other Comprehensive Income (A+B), net of tax | C32: -5.68 | D32: -225.66 | E32: 13.04 | F32: 31.96 | G32: 114.56 | I32: 0 | J32: 0 | K32: 0 | L32: 0 | M32: 0
B33: TOTAL COMPREHENSIVE INCOME FOR THE YEAR | C33: 3201.07 | D33: 2859.15 | E33: 4208.37 | F33: 5589.65 | G33: 3824.27 | I33: =I31+I32 -> 4214.434 | J33: =J31+J32 -> 4549.7888 | K33: =K31+K32 -> 4908.8479 | L33: =L31+L32 -> 5293.4996 | M33: =M31+M32 -> 5649.3305
B34: PROFIT FOR THE YEAR ATTRIBUTABLE TO:
B35: Owners of the Company | C35: 3139.29 | D35: 3030.57 | E35: 4106.45 | F35: 5460.23 | G35: 3667.23 | I35: =I31*(1-Assumptions!I30) -> 4165.968 | J35: =J31*(1-Assumptions!J30) -> 4497.4662 | K35: =K31*(1-Assumptions!K30) -> 4852.3962 | L35: =L31*(1-Assumptions!L30) -> 5232.6244 | M35: =M31*(1-Assumptions!M30) -> 5584.3632
B36: Non-Controlling interest | C36: 67.46 | D36: 54.24 | E36: 88.88 | F36: 97.46 | G36: 42.48 | I36: =I31*Assumptions!I30 -> 48.465991 | J36: =J31*Assumptions!J30 -> 52.322571 | K36: =K31*Assumptions!K30 -> 56.451751 | L36: =L31*Assumptions!L30 -> 60.875246 | M36: =M31*Assumptions!M30 -> 64.967301
B37: Profit for the year - Total | C37: 3206.75 | D37: 3084.81 | E37: 4195.33 | F37: 5557.69 | G37: 3709.71 | I37: =I35+I36 -> 4214.434 | J37: =J35+J36 -> 4549.7888 | K37: =K35+K36 -> 4908.8479 | L37: =L35+L36 -> 5293.4996 | M37: =M35+M36 -> 5649.3305
B38: OTHER COMPREHENSIVE INCOME FOR THE YEAR ATTRIBUTABLE TO:
B39: Owners of the Company | C39: 4.13 | D39: -212.31 | E39: 24.51 | F39: 42.14 | G39: 153.25 | I39: =I32*(1-Assumptions!I30) -> 0 | J39: =J32*(1-Assumptions!J30) -> 0 | K39: =K32*(1-Assumptions!K30) -> 0 | L39: =L32*(1-Assumptions!L30) -> 0 | M39: =M32*(1-Assumptions!M30) -> 0
B40: Non-Controlling interest | C40: -9.81 | D40: -13.35 | E40: -11.47 | F40: -10.18 | G40: -38.69 | I40: =I32*Assumptions!I30 -> 0 | J40: =J32*Assumptions!J30 -> 0 | K40: =K32*Assumptions!K30 -> 0 | L40: =L32*Assumptions!L30 -> 0 | M40: =M32*Assumptions!M30 -> 0
B41: OCI for the year - Total | C41: -5.68 | D41: -225.66 | E41: 13.04 | F41: 31.96 | G41: 114.56 | I41: =I39+I40 -> 0 | J41: =J39+J40 -> 0 | K41: =K39+K40 -> 0 | L41: =L39+L40 -> 0 | M41: =M39+M40 -> 0
B42: TOTAL COMPREHENSIVE INCOME FOR THE YEAR ATTRIBUTABLE TO:
B43: Owners of the Company | C43: 3143.42 | D43: 2818.26 | E43: 4130.96 | F43: 5502.37 | G43: 3820.48 | I43: =I35+I39 -> 4165.968 | J43: =J35+J39 -> 4497.4662 | K43: =K35+K39 -> 4852.3962 | L43: =L35+L39 -> 5232.6244 | M43: =M35+M39 -> 5584.3632
B44: Non-Controlling interest | C44: 57.65 | D44: 40.89 | E44: 77.41 | F44: 87.28 | G44: 3.79 | I44: =I36+I40 -> 48.465991 | J44: =J36+J40 -> 52.322571 | K44: =K36+K40 -> 56.451751 | L44: =L36+L40 -> 60.875246 | M44: =M36+M40 -> 64.967301
B45: Total Comprehensive income - Total | C45: 3201.07 | D45: 2859.15 | E45: 4208.37 | F45: 5589.65 | G45: 3824.27 | I45: =I43+I44 -> 4214.434 | J45: =J43+J44 -> 4549.7888 | K45: =K43+K44 -> 4908.8479 | L45: =L43+L44 -> 5293.4996 | M45: =M43+M44 -> 5649.3305
B46: Earnings per equity share (Face value of Re 1 each)
B47: Basic (in Rs) | C47: 32.73 | D47: 31.59 | E47: 42.83 | F47: 56.95 | G47: 38.25 | I47: =I35/Assumptions!I$28 -> 43.431693 | J47: =J35/Assumptions!J$28 -> 46.887679 | K47: =K35/Assumptions!K$28 -> 50.58795 | L47: =L35/Assumptions!L$28 -> 54.551964 | M47: =M35/Assumptions!M$28 -> 58.218966
B48: Diluted (in Rs) | D48: 31.59 | E48: 42.82 | F48: 56.94 | G48: 38.25 | I48: =I47 -> 43.431693 | J48: =J47 -> 46.887679 | K48: =K47 -> 50.58795 | L48: =L47 -> 54.551964 | M48: =M47 -> 58.218966

Sheet Cash Flow Statement & Forecast
B1: Asian Paints Limited - Consolidated Statement of Cash Flows
B2: (₹ in Crores)
C3: Year ended | I3: Forecast
B4: Particulars | C4: 31.03.2021 | D4: 31.03.2022 | E4: 31.03.2023 | F4: 31.03.2024 | G4: 31.03.2025 | I4: 31.03.2026E | J4: 31.03.2027E | K4: 31.03.2028E | L4: 31.03.2029E | M4: 31.03.2030E
B5: (A) CASH FLOW FROM OPERATING ACTIVITIES
B6: Profit before tax | C6: 4304.35 | D6: 4187.72 | E6: 5688.83 | F6: 7347.77 | G6: 5103.07 | I6: ='Income Statement & Forecast'!I25 -> 5695.1811 | J6: ='Income Statement & Forecast'!J25 -> 6148.3632 | K6: ='Income Statement & Forecast'!K25 -> 6633.5783 | L6: ='Income Statement & Forecast'!L25 -> 7153.3779 | M6: ='Income Statement & Forecast'!M25 -> 7634.2304
B7: Profit before tax from Discontinued operations | I7: 0 | J7: 0 | K7: 0 | L7: 0 | M7: 0
B8: Adjustments for:
B9: Depreciation and amortisation expense | C9: 791.27 | D9: 816.36 | E9: 858.02 | F9: 853 | G9: 1026.34 | I9: ='Income Statement & Forecast'!I20 -> 1108.4472 | J9: ='Income Statement & Forecast'!J20 -> 1197.123 | K9: ='Income Statement & Forecast'!K20 -> 1292.8928 | L9: ='Income Statement & Forecast'!L20 -> 1396.3242 | M9: ='Income Statement & Forecast'!M20 -> 1508.0302
B10: (Gain)/Loss on disposal of property, plant and equipment and other intangible assets | C10: -3.2 | D10: -44.36 | E10: -11.72 | F10: -2.08 | G10: -3.37 | I10: 0 | J10: 0 | K10: 0 | L10: 0 | M10: 0
B11: Net gain on modification/termination of leases | D11: -4.27 | E11: -2.96 | F11: -5.5 | G11: -2.07 | I11: 0 | J11: 0 | K11: 0 | L11: 0 | M11: 0
B12: Finance costs | C12: 91.63 | D12: 95.41 | E12: 144.45 | F12: 205.17 | G12: 227.02 | I12: ='Income Statement & Forecast'!I19 -> 233.60972 | J12: ='Income Statement & Forecast'!J19 -> 252.2985 | K12: ='Income Statement & Forecast'!K19 -> 272.48238 | L12: ='Income Statement & Forecast'!L19 -> 294.28097 | M12: ='Income Statement & Forecast'!M19 -> 314.88064
B13: Allowances for doubtful debts and advances | C13: 33.43 | D13: 57.56 | E13: 63.91 | F13: 116.64 | I13: 0 | J13: 0 | K13: 0 | L13: 0 | M13: 0
B14: Allowance for expected credit losses on receivables (trade & others) and advances | G14: 245.18 | I14: 0 | J14: 0 | K14: 0 | L14: 0 | M14: 0
B15: Bad debts written off (net) | C15: 3.42 | D15: 2.15 | E15: 3.44 | F15: 9.2 | G15: 6.06 | I15: 0 | J15: 0 | K15: 0 | L15: 0 | M15: 0
B16: Interest income | C16: -67.32 | D16: -92.72 | E16: -120.8 | F16: -169.93 | G16: -179.84 | I16: 0 | J16: 0 | K16: 0 | L16: 0 | M16: 0
B17: Dividend income | C17: -7.81 | D17: -15.16 | E17: -13.48 | F17: -20.16 | G17: -20.64 | I17: 0 | J17: 0 | K17: 0 | L17: 0 | M17: 0
B18: Share of profit in Associates | C18: -28.6 | D18: -31.57 | E18: -93.85 | F18: -133 | G18: -140.71 | I18: =-'Income Statement & Forecast'!I22 -> -147.7455 | J18: =-'Income Statement & Forecast'!J22 -> -155.13278 | K18: =-'Income Statement & Forecast'!K22 -> -162.88941 | L18: =-'Income Statement & Forecast'!L22 -> -171.03388 | M18: =-'Income Statement & Forecast'!M22 -> -179.58558
B19: Impairment loss on Goodwill (Causeway Lanka) | D19: 13.47 | E19: 24.66 | I19: 0 | J19: 0 | K19: 0 | L19: 0 | M19: 0
B20: Impairment loss on Goodwill and Intangible assets | G20: 223.25 | I20: 0 | J20: 0 | K20: 0 | L20: 0 | M20: 0
B21: Net gain on financial assets measured at FVTPL | C21: -18.33 | D21: -76.09 | E21: -120.61 | F21: -229.63 | G21: -182.43 | I21: 0 | J21: 0 | K21: 0 | L21: 0 | M21: 0
B22: Fair valuation loss on earnout, derivatives and gross obligation towards acquisition | E22: 28.85 | F22: -63.68 | I22: 0 | J22: 0 | K22: 0 | L22: 0 | M22: 0
B23: Fair valuation gain on stake acquisition obligation | C23: -22.44 | G23: -18.29 | I23: 0 | J23: 0 | K23: 0 | L23: 0 | M23: 0
B24: Fair valuation gain on previously held equity interest | F24: -33.96 | I24: 0 | J24: 0 | K24: 0 | L24: 0 | M24: 0
B25: Loss on sale/disposal of subsidiaries | G25: 83.71 | I25: 0 | J25: 0 | K25: 0 | L25: 0 | M25: 0
B26: Share based payment expense (net) | D26: 10.94 | E26: 13.38 | F26: 21.84 | G26: 21.25 | I26: 0 | J26: 0 | K26: 0 | L26: 0 | M26: 0
B27: Provision/(Reversal) for expected credit loss on government grants | D27: 53.73 | E27: -27.58 | F27: -10.9 | G27: -1.78 | I27: 0 | J27: 0 | K27: 0 | L27: 0 | M27: 0
B28: Deferred income arising from government grant | C28: -2.28 | D28: -1.76 | E28: -1.54 | F28: -5.29 | G28: -4.69 | I28: 0 | J28: 0 | K28: 0 | L28: 0 | M28: 0
B29: Net unrealised foreign exchange (gain)/loss | C29: -12.31 | D29: 57.6 | E29: 21.94 | F29: 8 | G29: -11.06 | I29: 0 | J29: 0 | K29: 0 | L29: 0 | M29: 0
B30: Other non cash adjustment | I30: 0 | J30: 0 | K30: 0 | L30: 0 | M30: 0
B31: Effect of exchange rates on translation of operating cashflows | C31: -92.28 | D31: -71.61 | E31: 4.88 | F31: 41.11 | G31: 18.66 | I31: 0 | J31: 0 | K31: 0 | L31: 0 | M31: 0
B32: Operating Profit before working capital changes | C32: 4969.53 | D32: 4957.4 | E32: 6459.82 | F32: 7928.6 | G32: 6389.66 | I32: =I6+I9+I12+I18 -> 6889.4925 | J32: =J6+J9+J12+J18 -> 7442.6519 | K32: =K6+K9+K12+K18 -> 8036.0641 | L32: =L6+L9+L12+L18 -> 8672.9492 | M32: =M6+M9+M12+M18 -> 9277.5556
B33: Adjustments for working capital:
B34: Decrease/(Increase) in trade receivables | C34: -1341.51 | D34: -1326.48 | E34: -833.94 | F34: -361.89 | G34: 281.8 | I34: =-('Balance Sheet & Forecast'!I26-'Balance Sheet & Forecast'!G26) -> -650.1151 | J34: =-('Balance Sheet & Forecast'!J26-'Balance Sheet & Forecast'!I26) -> -397.10121 | K34: =-('Balance Sheet & Forecast'!K26-'Balance Sheet & Forecast'!J26) -> -428.8693 | L34: =-('Balance Sheet & Forecast'!L26-'Balance Sheet & Forecast'!K26) -> -463.17885 | M34: =-('Balance Sheet & Forecast'!M26-'Balance Sheet & Forecast'!L26) -> -437.70401
B35: Decrease/(Increase) in financial assets | D35: -130.62 | E35: 156.75 | F35: 23.12 | G35: 6.71 | I35: 0 | J35: 0 | K35: 0 | L35: 0 | M35: 0
B36: (Increase)/Decrease in inventories | C36: -408.79 | D36: -2354.38 | E36: -55.98 | F36: 314.94 | G36: -805.34 | I36: =-('Balance Sheet & Forecast'!I23-'Balance Sheet & Forecast'!G23) -> -602.28352 | J36: =-('Balance Sheet & Forecast'!J23-'Balance Sheet & Forecast'!I23) -> -585.72428 | K36: =-('Balance Sheet & Forecast'!K23-'Balance Sheet & Forecast'!J23) -> -632.58222 | L36: =-('Balance Sheet & Forecast'!L23-'Balance Sheet & Forecast'!K23) -> -683.1888 | M36: =-('Balance Sheet & Forecast'!M23-'Balance Sheet & Forecast'!L23) -> -645.61342
B37: Decrease/(Increase) in other assets | D37: -21.21 | E37: -26.71 | F37: -260.89 | G37: 1.71 | I37: 0 | J37: 0 | K37: 0 | L37: 0 | M37: 0
B38: (Decrease)/Increase in trade payables | C38: 1543.84 | D38: 644.02 | E38: -538.97 | F38: 268.58 | G38: -160.41 | I38: =('Balance Sheet & Forecast'!I56+'Balance Sheet & Forecast'!I57)-('Balance Sheet & Forecast'!G56+'Balance Sheet & Forecast'!G57) -> 252.06997 | J38: =('Balance Sheet & Forecast'!J56+'Balance Sheet & Forecast'!J57)-('Balance Sheet & Forecast'!I56+'Balance Sheet & Forecast'!I57) -> 328.0056 | K38: =('Balance Sheet & Forecast'!K56+'Balance Sheet & Forecast'!K57)-('Balance Sheet & Forecast'!J56+'Balance Sheet & Forecast'!J57) -> 354.24605 | L38: =('Balance Sheet & Forecast'!L56+'Balance Sheet & Forecast'!L57)-('Balance Sheet & Forecast'!K56+'Balance Sheet & Forecast'!K57) -> 382.58573 | M38: =('Balance Sheet & Forecast'!M56+'Balance Sheet & Forecast'!M57)-('Balance Sheet & Forecast'!L56+'Balance Sheet & Forecast'!L57) -> 361.54351
B39: Increase in other financial liabilities | D39: 237.19 | E39: 441.1 | F39: 16.4 | G39: 82.56 | I39: 0 | J39: 0 | K39: 0 | L39: 0 | M39: 0
B40: Increase in other liabilities and provisions | D40: 156.26 | E40: 85.64 | F40: 9.79 | G40: 22.79 | I40: 0 | J40: 0 | K40: 0 | L40: 0 | M40: 0
B41: Cash generated from Operating activities | C41: 4763.07 | D41: 2162.18 | E41: 5687.71 | F41: 7938.65 | G41: 5819.48 | I41: =I32+SUM(I34:I40) -> 5889.1639 | J41: =J32+SUM(J34:J40) -> 6787.832 | K41: =K32+SUM(K34:K40) -> 7328.8586 | L41: =L32+SUM(L34:L40) -> 7909.1673 | M41: =M32+SUM(M34:M40) -> 8555.7817
B42: Income Tax paid (net of refund) | C42: -1079.72 | D42: -1175.69 | E42: -1494.28 | F42: -1835.05 | G42: -1395.52 | I42: =-'Income Statement & Forecast'!I30 -> -1480.7471 | J42: =-'Income Statement & Forecast'!J30 -> -1598.5744 | K42: =-'Income Statement & Forecast'!K30 -> -1724.7304 | L42: =-'Income Statement & Forecast'!L30 -> -1859.8782 | M42: =-'Income Statement & Forecast'!M30 -> -1984.8999
B43: Net Cash generated from Operating activities | C43: 3683.35 | D43: 986.49 | E43: 4193.43 | F43: 6103.6 | G43: 4423.96 | I43: =I41+I42 -> 4408.4168 | J43: =J41+J42 -> 5189.2576 | K43: =K41+K42 -> 5604.1282 | L43: =L41+L42 -> 6049.289 | M43: =M41+M42 -> 6570.8818
B44: (B) CASH FLOW FROM INVESTING ACTIVITIES
B45: Purchase of property, plant and equipment and other intangible assets | C45: -281.87 | D45: -538.24 | E45: -1273.37 | F45: -2199.01 | G45: -1805.32 | I45: =-Assumptions!I23*Assumptions!I6 -> -2515.797 | J45: =-Assumptions!J23*Assumptions!J6 -> -2717.0608 | K45: =-Assumptions!K23*Assumptions!K6 -> -2515.222 | L45: =-Assumptions!L23*Assumptions!L6 -> -2716.4397 | M45: =-Assumptions!M23*Assumptions!M6 -> -2906.5905
B46: Sale of property, plant and equipment | C46: 27.61 | D46: 39.58 | E46: 25.92 | F46: 5.13 | G46: 10.1 | I46: 0 | J46: 0 | K46: 0 | L46: 0 | M46: 0
B47: Payment for acquiring right-of-use assets | C47: -6.84 | D47: -12.46 | E47: -172.24 | F47: -297.07 | G47: -24.75 | I47: 0 | J47: 0 | K47: 0 | L47: 0 | M47: 0
B48: Purchase of non-current investments | C48: -0.5 | E48: -146.07 | F48: -212.24 | G48: -0.92 | I48: 0 | J48: 0 | K48: 0 | L48: 0 | M48: 0
B49: Sale of non-current investments | C49: 272.32 | D49: 146.46 | E49: 376.61 | F49: 0.5 | I49: 0 | J49: 0 | K49: 0 | L49: 0 | M49: 0
B50: Sale/(Purchase) of current investments (net) | C50: -139.34 | D50: 61.03 | E50: 69.43 | F50: 239.99 | G50: 420.65 | I50: 0 | J50: 0 | K50: 0 | L50: 0 | M50: 0
B51: Proceeds from/(Purchase of) term deposits (net) | C51: -500.33 | D51: -110.21 | E51: -118.71 | F51: -206.25 | G51: 196.8 | I51: 0 | J51: 0 | K51: 0 | L51: 0 | M51: 0
B52: Investment in Associate | E52: -179.62 | I52: 0 | J52: 0 | K52: 0 | L52: 0 | M52: 0
B53: Proceeds from disposal of subsidiaries (net) | G53: 38.29 | I53: 0 | J53: 0 | K53: 0 | L53: 0 | M53: 0
B54: Amount paid for acquiring controlling stake | F54: -75 | I54: 0 | J54: 0 | K54: 0 | L54: 0 | M54: 0
B55: Payment of earnout | F55: -37.71 | I55: 0 | J55: 0 | K55: 0 | L55: 0 | M55: 0
B56: Interest received | C56: 73.35 | D56: 76.99 | E56: 87.15 | F56: 135.49 | G56: 154.89 | I56: 0 | J56: 0 | K56: 0 | L56: 0 | M56: 0
B57: Dividend received from Associate | E57: 42.78 | F57: 108.37 | G57: 115.5 | I57: 0 | J57: 0 | K57: 0 | L57: 0 | M57: 0
B58: Dividend received from others | C58: 7.81 | D58: 15.16 | E58: 13.48 | F58: 20.17 | G58: 20.64 | I58: 0 | J58: 0 | K58: 0 | L58: 0 | M58: 0
B59: Net Cash used in Investing activities | C59: -547.79 | D59: -321.69 | E59: -1274.64 | F59: -2517.63 | G59: -874.12 | I59: =SUM(I45:I58) -> -2515.797 | J59: =SUM(J45:J58) -> -2717.0608 | K59: =SUM(K45:K58) -> -2515.222 | L59: =SUM(L45:L58) -> -2716.4397 | M59: =SUM(M45:M58) -> -2906.5905
B60: (C) CASH FLOW FROM FINANCING ACTIVITIES
B61: Proceeds from long term borrowings | C61: 2.14 | D61: 39.87 | E61: 94 | F61: 5.91 | G61: 219.84 | I61: 0 | J61: 0 | K61: 0 | L61: 0 | M61: 0
B62: Repayment of long term borrowings | C62: -14.21 | D62: -7.89 | E62: -15.55 | F62: -14.17 | G62: -21.16 | I62: 0 | J62: 0 | K62: 0 | L62: 0 | M62: 0
B63: Proceeds/(Repayment) from short term borrowings (net) | C63: 37.78 | D63: 292.68 | E63: 159.76 | F63: 94.98 | G63: -406.41 | I63: 0 | J63: 0 | K63: 0 | L63: 0 | M63: 0
B64: Acceptances (net) | C64: 115.5 | D64: 85.35 | E64: -8.97 | F64: -83.65 | G64: 194.74 | I64: 0 | J64: 0 | K64: 0 | L64: 0 | M64: 0
B65: Amount infused by non-controlling shareholders in subsidiary | F65: 40.6 | I65: 0 | J65: 0 | K65: 0 | L65: 0 | M65: 0
B66: Repayment of principal portion of lease liabilities | C66: -202.95 | D66: -221.4 | E66: -255.72 | F66: -285.63 | G66: -324.62 | I66: 0 | J66: 0 | K66: 0 | L66: 0 | M66: 0
B67: Transactions with non-controlling interest | D67: -64.91 | G67: -34.65 | I67: 0 | J67: 0 | K67: 0 | L67: 0 | M67: 0
B68: Finance costs paid (including lease interest) | C68: -89.31 | D68: -93.56 | E68: -141.95 | F68: -190.57 | G68: -203.19 | I68: =-'Income Statement & Forecast'!I19 -> -233.60972 | J68: =-'Income Statement & Forecast'!J19 -> -252.2985 | K68: =-'Income Statement & Forecast'!K19 -> -272.48238 | L68: =-'Income Statement & Forecast'!L19 -> -294.28097 | M68: =-'Income Statement & Forecast'!M19 -> -314.88064
B69: Treasury shares - ESOP Trust transactions (net) | D69: -74.95 | E69: -35.57 | F69: 0.91 | G69: -36.92 | I69: 0 | J69: 0 | K69: 0 | L69: 0 | M69: 0
B70: Dividend paid (including dividend paid to non-controlling shareholders) | C70: -499.35 | D70: -1762.8 | E70: -1936.05 | F70: -2550.88 | G70: -3140.21 | I70: =-Assumptions!I25*'Income Statement & Forecast'!I31 -> -2950.1038 | J70: =-Assumptions!J25*'Income Statement & Forecast'!J31 -> -3184.8521 | K70: =-Assumptions!K25*'Income Statement & Forecast'!K31 -> -3436.1936 | L70: =-Assumptions!L25*'Income Statement & Forecast'!L31 -> -3705.4497 | M70: =-Assumptions!M25*'Income Statement & Forecast'!M31 -> -3954.5313
B71: Net Cash used in Financing activities | C71: -650.4 | D71: -1807.61 | E71: -2140.05 | F71: -2982.5 | G71: -3752.58 | I71: =SUM(I61:I70) -> -3183.7135 | J71: =SUM(J61:J70) -> -3437.1506 | K71: =SUM(K61:K70) -> -3708.6759 | L71: =SUM(L61:L70) -> -3999.7307 | M71: =SUM(M61:M70) -> -4269.412
B72: (D) NET CHANGE IN CASH AND CASH EQUIVALENTS
B73: NET INCREASE/(DECREASE) IN CASH AND CASH EQUIVALENTS [A+B+C] | C73: 2485.16 | D73: -1142.81 | E73: 778.74 | F73: 603.47 | G73: -202.74 | I73: =I43+I59+I71 -> -1291.0937 | J73: =J43+J59+J71 -> -964.95382 | K73: =K43+K59+K71 -> -619.76967 | L73: =L43+L59+L71 -> -666.8814 | M73: =M43+M59+M71 -> -605.12067
B74: Cash and cash equivalents as at 1st April | C74: 928.75 | D74: 3421.16 | E74: 2283.29 | F74: 3054.33 | G74: 3626.95 | I74: =G76 -> 3357.42 | J74: =I76 -> 2066.3263 | K74: =J76 -> 1101.3724 | L74: =K76 -> 481.60276 | M74: =L76 -> -185.27864
B75: Net effect of exchange (loss)/gain on cash and cash equivalents | C75: 7.25 | D75: 4.94 | E75: -7.7 | F75: -30.85 | G75: -66.79 | I75: 0 | J75: 0 | K75: 0 | L75: 0 | M75: 0
B76: Cash and cash equivalents as at 31st March | C76: 3421.16 | D76: 2283.29 | E76: 3054.33 | F76: 3626.95 | G76: 3357.42 | I76: =I74+I73+I75 -> 2066.3263 | J76: =J74+J73+J75 -> 1101.3724 | K76: =K74+K73+K75 -> 481.60276 | L76: =L74+L73+L75 -> -185.27864 | M76: =M74+M73+M75 -> -790.39931

Sheet Summary
B1: ASIAN PAINTS LIMITED
B2: Executive Summary | Five-Year Forecast
B4: SELECT YEAR | C4: 31.03.2030E | D4: vs | E4: COMPARE TO | F4: 31.03.2025
B6: Revenue | C6: EBITDA | D6: EBITDA Margin | E6: PAT | F6: ROE | G6: EPS (Basic)
B7: =INDEX('Income Statement & Forecast'!C10:M10,MATCH(C4,'Income Statement & Forecast'!C4:M4,0)) -> 49243.175 | C7: =INDEX('Income Statement & Forecast'!C18:M18,MATCH(C4,'Income Statement & Forecast'!C4:M4,0)) -> 9277.5556 | D7: =C7/B7 -> 0.18840287 | E7: =INDEX('Income Statement & Forecast'!C31:M31,MATCH(C4,'Income Statement & Forecast'!C4:M4,0)) -> 5649.3305 | F7: =E7/INDEX('Balance Sheet & Forecast'!C41:M41,MATCH(C4,'Balance Sheet & Forecast'!C4:M4,0)) -> 0.20585073 | G7: =INDEX('Income Statement & Forecast'!C47:M47,MATCH(C4,'Income Statement & Forecast'!C4:M4,0)) -> 58.218966
B8: ₹ Crores | C8: ₹ Crores | D8: of revenue | E8: ₹ Crores | F8: PAT / Equity | G8: ₹ per share
B9: {=IFERROR(B7/INDEX($C$76:$L$76,$C$72)-1,"")} -> 0.42823965 | C9: {=IFERROR(C7/INDEX($C$77:$L$77,$C$72)-1,"")} -> 0.41021576 | D9: {=IFERROR(D7-INDEX($C$78:$L$78,$C$72),"")} -> -0.0024079666 | E9: {=IFERROR(E7/INDEX($C$79:$L$79,$C$72)-1,"")} -> 0.52284963 | F9: {=IFERROR(F7-INDEX($C$82:$L$82,$C$72),"")} -> 0.020911266 | G9: {=IFERROR(G7/INDEX($C$81:$L$81,$C$72)-1,"")} -> 0.52206446
C10: Historical (FY2021 - FY2025) | H10: Forecast (FY2026E - FY2030E)
B11: Particulars | C11: ='Income Statement & Forecast'!C4 -> 31.03.2021 | D11: ='Income Statement & Forecast'!D4 -> 31.03.2022 | E11: ='Income Statement & Forecast'!E4 -> 31.03.2023 | F11: ='Income Statement & Forecast'!F4 -> 31.03.2024 | G11: ='Income Statement & Forecast'!G4 -> 31.03.2025 | I11: ='Income Statement & Forecast'!I4 -> 31.03.2026E | J11: ='Income Statement & Forecast'!J4 -> 31.03.2027E | K11: ='Income Statement & Forecast'!K4 -> 31.03.2028E | L11: ='Income Statement & Forecast'!L4 -> 31.03.2029E | M11: ='Income Statement & Forecast'!M4 -> 31.03.2030E
B12: KEY FINANCIAL HIGHLIGHTS
B13: =HYPERLINK("#'Income Statement & Forecast'!B10","Revenue from Operations") -> Revenue from Operations | C13: =Assumptions!C6 -> 21712.79 | D13: =Assumptions!D6 -> 29101.28 | E13: =Assumptions!E6 -> 34488.59 | F13: =Assumptions!F6 -> 35494.73 | G13: =Assumptions!G6 -> 33905.62 | I13: =Assumptions!I6 -> 35939.957 | J13: =Assumptions!J6 -> 38815.154 | K13: =Assumptions!K6 -> 41920.366 | L13: =Assumptions!L6 -> 45273.995 | M13: =Assumptions!M6 -> 48443.175
B14: Revenue Growth | D14: =D13/C13-1 -> 0.34028285 | E14: =E13/D13-1 -> 0.18512278 | F14: =F13/E13-1 -> 0.029173127 | G14: =G13/F13-1 -> -0.044770308 | I14: =I13/G13-1 -> 0.06 | J14: =J13/I13-1 -> 0.08 | K14: =K13/J13-1 -> 0.08 | L14: =L13/K13-1 -> 0.08 | M14: =M13/L13-1 -> 0.07
B15: =HYPERLINK("#'Income Statement & Forecast'!B18","EBITDA") -> EBITDA | C15: ='Income Statement & Forecast'!C18 -> 5158.65 | D15: ='Income Statement & Forecast'!D18 -> 5183.62 | E15: ='Income Statement & Forecast'!E18 -> 6646.32 | F15: ='Income Statement & Forecast'!F18 -> 8272.94 | G15: ='Income Statement & Forecast'!G18 -> 6578.82 | I15: ='Income Statement & Forecast'!I18 -> 6889.4925 | J15: ='Income Statement & Forecast'!J18 -> 7442.6519 | K15: ='Income Statement & Forecast'!K18 -> 8036.0641 | L15: ='Income Statement & Forecast'!L18 -> 8672.9492 | M15: ='Income Statement & Forecast'!M18 -> 9277.5556
B16: EBITDA Margin | C16: =C15/C13 -> 0.23758577 | D16: =D15/D13 -> 0.17812344 | E16: =E15/E13 -> 0.19271069 | F16: =F15/F13 -> 0.23307516 | G16: =G15/G13 -> 0.19403332 | I16: =I15/I13 -> 0.19169451 | J16: =J15/J13 -> 0.19174604 | K16: =K15/K13 -> 0.19169833 | L16: =L15/L13 -> 0.1915658 | M16: =M15/M13 -> 0.19151419
B17: EBIT | C17: ='Income Statement & Forecast'!C18-'Income Statement & Forecast'!C20 -> 4367.38 | D17: ='Income Statement & Forecast'!D18-'Income Statement & Forecast'!D20 -> 4367.26 | E17: ='Income Statement & Forecast'!E18-'Income Statement & Forecast'!E20 -> 5788.3 | F17: ='Income Statement & Forecast'!F18-'Income Statement & Forecast'!F20 -> 7419.94 | G17: ='Income Statement & Forecast'!G18-'Income Statement & Forecast'!G20 -> 5552.48 | I17: ='Income Statement & Forecast'!I18-'Income Statement & Forecast'!I20 -> 5781.0453 | J17: ='Income Statement & Forecast'!J18-'Income Statement & Forecast'!J20 -> 6245.5289 | K17: ='Income Statement & Forecast'!K18-'Income Statement & Forecast'!K20 -> 6743.1712 | L17: ='Income Statement & Forecast'!L18-'Income Statement & Forecast'!L20 -> 7276.6249 | M17: ='Income Statement & Forecast'!M18-'Income Statement & Forecast'!M20 -> 7769.5255
B18: EBIT Margin | C18: =C17/C13 -> 0.2011432 | D18: =D17/D13 -> 0.15007106 | E18: =E17/E13 -> 0.16783232 | F18: =F17/F13 -> 0.20904343 | G18: =G17/G13 -> 0.16376282 | I18: =I17/I13 -> 0.16085287 | J18: =J17/J13 -> 0.1609044 | K18: =K17/K13 -> 0.16085669 | L18: =L17/L13 -> 0.16072416 | M18: =M17/M13 -> 0.16038432
B19: =HYPERLINK("#'Income Statement & Forecast'!B31","Profit After Tax (PAT)") -> Profit After Tax (PAT) | C19: ='Income Statement & Forecast'!C31 -> 3206.75 | D19: ='Income Statement & Forecast'!D31 -> 3084.81 | E19: ='Income Statement & Forecast'!E31 -> 4195.33 | F19: ='Income Statement & Forecast'!F31 -> 5557.69 | G19: ='Income Statement & Forecast'!G31 -> 3709.71 | I19: ='Income Statement & Forecast'!I31 -> 4214.434 | J19: ='Income Statement & Forecast'!J31 -> 4549.7888 | K19: ='Income Statement & Forecast'!K31 -> 4908.8479 | L19: ='Income Statement & Forecast'!L31 -> 5293.4996 | M19: ='Income Statement & Forecast'!M31 -> 5649.3305
B20: PAT Margin | C20: =C19/C13 -> 0.14768945 | D20: =D19/D13 -> 0.10600255 | E20: =E19/E13 -> 0.121644 | F20: =F19/F13 -> 0.15657789 | G20: =G19/G13 -> 0.10941283 | I20: =I19/I13 -> 0.11726319 | J20: =J19/J13 -> 0.11721682 | K20: =K19/K13 -> 0.11709936 | L20: =L19/L13 -> 0.11692142 | M20: =M19/M13 -> 0.11661768
B22: BALANCE SHEET SUMMARY
B23: =HYPERLINK("#'Balance Sheet & Forecast'!B34","Total Assets") -> Total Assets | C23: ='Balance Sheet & Forecast'!C34 -> 20369.62 | D23: ='Balance Sheet & Forecast'!D34 -> 22984.45 | E23: ='Balance Sheet & Forecast'!E34 -> 25798 | F23: ='Balance Sheet & Forecast'!F34 -> 29924.09 | G23: ='Balance Sheet & Forecast'!G34 -> 30371.37 | I23: ='Balance Sheet & Forecast'!I34 -> 31887.77 | J23: ='Balance Sheet & Forecast'!J34 -> 33580.712 | K23: ='Balance Sheet & Forecast'!K34 -> 35407.613 | L23: ='Balance Sheet & Forecast'!L34 -> 37378.248 | M23: ='Balance Sheet & Forecast'!M34 -> 39434.591
B24: =HYPERLINK("#'Balance Sheet & Forecast'!B41","Total Equity") -> Total Equity | C24: ='Balance Sheet & Forecast'!C41 -> 13229.15 | D24: ='Balance Sheet & Forecast'!D41 -> 14199.09 | E24: ='Balance Sheet & Forecast'!E41 -> 16445.89 | F24: ='Balance Sheet & Forecast'!F41 -> 19423.68 | G24: ='Balance Sheet & Forecast'!G41 -> 20059.05 | I24: ='Balance Sheet & Forecast'!I41 -> 21323.38 | J24: ='Balance Sheet & Forecast'!J41 -> 22688.317 | K24: ='Balance Sheet & Forecast'!K41 -> 24160.971 | L24: ='Balance Sheet & Forecast'!L41 -> 25749.021 | M24: ='Balance Sheet & Forecast'!M41 -> 27443.82
B25: Total Borrowings (NC + Current) | C25: ='Balance Sheet & Forecast'!C44+'Balance Sheet & Forecast'!C53 -> 340.23 | D25: ='Balance Sheet & Forecast'!D44+'Balance Sheet & Forecast'!D53 -> 775.66 | E25: ='Balance Sheet & Forecast'!E44+'Balance Sheet & Forecast'!E53 -> 972.21 | F25: ='Balance Sheet & Forecast'!F44+'Balance Sheet & Forecast'!F53 -> 1107.14 | G25: ='Balance Sheet & Forecast'!G44+'Balance Sheet & Forecast'!G53 -> 863.75 | I25: ='Balance Sheet & Forecast'!I44+'Balance Sheet & Forecast'!I53 -> 863.75 | J25: ='Balance Sheet & Forecast'!J44+'Balance Sheet & Forecast'!J53 -> 863.75 | K25: ='Balance Sheet & Forecast'!K44+'Balance Sheet & Forecast'!K53 -> 863.75 | L25: ='Balance Sheet & Forecast'!L44+'Balance Sheet & Forecast'!L53 -> 863.75 | M25: ='Balance Sheet & Forecast'!M44+'Balance Sheet & Forecast'!M53 -> 863.75
B26: Cash and Cash Equivalents | C26: ='Balance Sheet & Forecast'!C27 -> 346.39 | D26: ='Balance Sheet & Forecast'!D27 -> 621.72 | E26: ='Balance Sheet & Forecast'!E27 -> 523.1 | F26: ='Balance Sheet & Forecast'!F27 -> 829.34 | G26: ='Balance Sheet & Forecast'!G27 -> 445.28 | I26: ='Balance Sheet & Forecast'!I27 -> -845.81375 | J26: ='Balance Sheet & Forecast'!J27 -> -1810.7676 | K26: ='Balance Sheet & Forecast'!K27 -> -2430.5372 | L26: ='Balance Sheet & Forecast'!L27 -> -3097.4186 | M26: ='Balance Sheet & Forecast'!M27 -> -3702.5393
B27: Net Debt / (Net Cash) | C27: =C25-C26 -> -6.16 | D27: =D25-D26 -> 153.94 | E27: =E25-E26 -> 449.11 | F27: =F25-F26 -> 277.8 | G27: =G25-G26 -> 418.47 | I27: =I25-I26 -> 1709.5637 | J27: =J25-J26 -> 2674.5176 | K27: =K25-K26 -> 3294.2872 | L27: =L25-L26 -> 3961.1686 | M27: =M25-M26 -> 4566.2893
B28: Net Debt to Equity | C28: =C27/C24 -> -0.00046563838 | D28: =D27/D24 -> 0.01084154 | E28: =E27/E24 -> 0.027308343 | F28: =F27/F24 -> 0.01430213 | G28: =G27/G24 -> 0.020861905 | I28: =I27/I24 -> 0.080173206 | J28: =J27/J24 -> 0.11788083 | K28: =K27/K24 -> 0.13634747 | L28: =L27/L24 -> 0.15383764 | M28: =M27/M24 -> 0.1663868
B30: CASH FLOW SUMMARY
B31: =HYPERLINK("#'Cash Flow Statement & Forecast'!B43","Cash from Operations (CFO)") -> Cash from Operations (CFO) | C31: ='Cash Flow Statement & Forecast'!C43 -> 3683.35 | D31: ='Cash Flow Statement & Forecast'!D43 -> 986.49 | E31: ='Cash Flow Statement & Forecast'!E43 -> 4193.43 | F31: ='Cash Flow Statement & Forecast'!F43 -> 6103.6 | G31: ='Cash Flow Statement & Forecast'!G43 -> 4423.96 | I31: ='Cash Flow Statement & Forecast'!I43 -> 4408.4168 | J31: ='Cash Flow Statement & Forecast'!J43 -> 5189.2576 | K31: ='Cash Flow Statement & Forecast'!K43 -> 5604.1282 | L31: ='Cash Flow Statement & Forecast'!L43 -> 6049.289 | M31: ='Cash Flow Statement & Forecast'!M43 -> 6570.8818
B32: Capital Expenditure | C32: ='Cash Flow Statement & Forecast'!C45 -> -281.87 | D32: ='Cash Flow Statement & Forecast'!D45 -> -538.24 | E32: ='Cash Flow Statement & Forecast'!E45 -> -1273.37 | F32: ='Cash Flow Statement & Forecast'!F45 -> -2199.01 | G32: ='Cash Flow Statement & Forecast'!G45 -> -1805.32 | I32: ='Cash Flow Statement & Forecast'!I45 -> -2515.797 | J32: ='Cash Flow Statement & Forecast'!J45 -> -2717.0608 | K32: ='Cash Flow Statement & Forecast'!K45 -> -2515.222 | L32: ='Cash Flow Statement & Forecast'!L45 -> -2716.4397 | M32: ='Cash Flow Statement & Forecast'!M45 -> -2906.5905
B33: Free Cash Flow (CFO + Capex) | C33: =C31+C32 -> 3401.48 | D33: =D31+D32 -> 448.25 | E33: =E31+E32 -> 2920.06 | F33: =F31+F32 -> 3904.59 | G33: =G31+G32 -> 2618.64 | I33: =I31+I32 -> 1892.6198 | J33: =J31+J32 -> 2472.1968 | K33: =K31+K32 -> 3088.9063 | L33: =L31+L32 -> 3332.8493 | M33: =M31+M32 -> 3664.2913
B34: Dividends Paid | C34: ='Cash Flow Statement & Forecast'!C70 -> -499.35 | D34: ='Cash Flow Statement & Forecast'!D70 -> -1762.8 | E34: ='Cash Flow Statement & Forecast'!E70 -> -1936.05 | F34: ='Cash Flow Statement & Forecast'!F70 -> -2550.88 | G34: ='Cash Flow Statement & Forecast'!G70 -> -3140.21 | I34: ='Cash Flow Statement & Forecast'!I70 -> -2950.1038 | J34: ='Cash Flow Statement & Forecast'!J70 -> -3184.8521 | K34: ='Cash Flow Statement & Forecast'!K70 -> -3436.1936 | L34: ='Cash Flow Statement & Forecast'!L70 -> -3705.4497 | M34: ='Cash Flow Statement & Forecast'!M70 -> -3954.5313
B36: KEY RATIOS
B37: Return on Equity (ROE) | C37: =C19/C24 -> 0.24240031 | D37: =D19/D24 -> 0.21725406 | E37: =E19/E24 -> 0.25509899 | F37: =F19/F24 -> 0.28612961 | G37: =G19/G24 -> 0.18493947 | I37: =I19/I24 -> 0.19764381 | J37: =J19/J24 -> 0.20053443 | K37: =K19/K24 -> 0.20317262 | L37: =L19/L24 -> 0.20558062 | M37: =M19/M24 -> 0.20585073
B38: Return on Assets (ROA) | C38: =C19/C23 -> 0.15742807 | D38: =D19/D23 -> 0.13421291 | E38: =E19/E23 -> 0.1626223 | F38: =F19/F23 -> 0.18572628 | G38: =G19/G23 -> 0.12214497 | I38: =I19/I23 -> 0.13216459 | J38: =J19/J23 -> 0.13548816 | K38: =K19/K23 -> 0.13863821 | L38: =L19/L23 -> 0.14161979 | M38: =M19/M23 -> 0.14325825
B39: Return on Capital Employed (ROCE) | C39: =C17/(C24+C25) -> 0.32185553 | D39: =D17/(D24+D25) -> 0.2916416 | E39: =E17/(E24+E25) -> 0.33231524 | F39: =F17/(F24+F25) -> 0.36140495 | G39: =G17/(G24+G25) -> 0.26537939 | I39: =I17/(I24+I25) -> 0.2605585 | J39: =J17/(J24+J25) -> 0.26517965 | K39: =K17/(K24+K25) -> 0.26946039 | L39: =L17/(L24+L25) -> 0.27342605 | M39: =M17/(M24+M25) -> 0.27446812
B40: Effective Tax Rate | C40: =Assumptions!C15 -> 0.25499785 | D40: =Assumptions!D15 -> 0.26336766 | E40: =Assumptions!E15 -> 0.26253201 | F40: =Assumptions!F15 -> 0.24362221 | G40: =Assumptions!G15 -> 0.27304348 | I40: =Assumptions!I15 -> 0.26 | J40: =Assumptions!J15 -> 0.26 | K40: =Assumptions!K15 -> 0.26 | L40: =Assumptions!L15 -> 0.26 | M40: =Assumptions!M15 -> 0.26
B41: CFO / Revenue | C41: =C31/C13 -> 0.16963965 | D41: =D31/D13 -> 0.033898509 | E41: =E31/E13 -> 0.12158891 | F41: =F31/F13 -> 0.17195792 | G41: =G31/G13 -> 0.13047866 | I41: =I31/I13 -> 0.1226606 | J41: =J31/J13 -> 0.13369154 | K41: =K31/K13 -> 0.1336851 | L41: =L31/L13 -> 0.13361509 | M41: =M31/M13 -> 0.13564102
B43: PER SHARE DATA
B44: =HYPERLINK("#'Income Statement & Forecast'!B47","Basic EPS (₹)") -> Basic EPS (₹) | C44: ='Income Statement & Forecast'!C47 -> 32.73 | D44: ='Income Statement & Forecast'!D47 -> 31.59 | E44: ='Income Statement & Forecast'!E47 -> 42.83 | F44: ='Income Statement & Forecast'!F47 -> 56.95 | G44: ='Income Statement & Forecast'!G47 -> 38.25 | I44: ='Income Statement & Forecast'!I47 -> 43.431693 | J44: ='Income Statement & Forecast'!J47 -> 46.887679 | K44: ='Income Statement & Forecast'!K47 -> 50.58795 | L44: ='Income Statement & Forecast'!L47 -> 54.551964 | M44: ='Income Statement & Forecast'!M47 -> 58.218966
B45: Book Value per Share (₹) | C45: ='Balance Sheet & Forecast'!C39/Assumptions!C28 -> 133.51011 | D45: ='Balance Sheet & Forecast'!D39/Assumptions!D28 -> 143.99041 | E45: ='Balance Sheet & Forecast'!E39/Assumptions!E28 -> 166.72467 | F45: ='Balance Sheet & Forecast'!F39/Assumptions!F28 -> 195.24917 | G45: ='Balance Sheet & Forecast'!G39/Assumptions!G28 -> 202.2499 | I45: ='Balance Sheet & Forecast'!I39/Assumptions!I28 -> 215.2794 | J45: ='Balance Sheet & Forecast'!J39/Assumptions!J28 -> 229.34571 | K45: ='Balance Sheet & Forecast'!K39/Assumptions!K28 -> 244.52209 | L45: ='Balance Sheet & Forecast'!L39/Assumptions!L28 -> 260.88768 | M45: ='Balance Sheet & Forecast'!M39/Assumptions!M28 -> 278.35337
B46: Dividend per Share (₹) | C46: =-'Cash Flow Statement & Forecast'!C70/Assumptions!C28 -> 5.2059008 | D46: =-'Cash Flow Statement & Forecast'!D70/Assumptions!D28 -> 18.377815 | E46: =-'Cash Flow Statement & Forecast'!E70/Assumptions!E28 -> 20.184008 | F46: =-'Cash Flow Statement & Forecast'!F70/Assumptions!F28 -> 26.593828 | G46: =-'Cash Flow Statement & Forecast'!G70/Assumptions!G28 -> 32.737802 | I46: =-'Cash Flow Statement & Forecast'!I70/Assumptions!I28 -> 30.755878 | J46: =-'Cash Flow Statement & Forecast'!J70/Assumptions!J28 -> 33.203212 | K46: =-'Cash Flow Statement & Forecast'!K70/Assumptions!K28 -> 35.823536 | L46: =-'Cash Flow Statement & Forecast'!L70/Assumptions!L28 -> 38.630627 | M46: =-'Cash Flow Statement & Forecast'!M70/Assumptions!M28 -> 41.227391
B47: Shares Outstanding (Crores) | C47: =Assumptions!C28 -> 95.92 | D47: =Assumptions!D28 -> 95.92 | E47: =Assumptions!E28 -> 95.92 | F47: =Assumptions!F28 -> 95.92 | G47: =Assumptions!G28 -> 95.92 | I47: =Assumptions!I28 -> 95.92 | J47: =Assumptions!J28 -> 95.92 | K47: =Assumptions!K28 -> 95.92 | L47: =Assumptions!L28 -> 95.92 | M47: =Assumptions!M28 -> 95.92
B49: BALANCE CHECK
B50: Balance Sheet Check (Assets - Equity & Liabilities) | C50: ='Balance Sheet & Forecast'!C65 -> 0 | D50: ='Balance Sheet & Forecast'!D65 -> 0 | E50: ='Balance Sheet & Forecast'!E65 -> 0 | F50: ='Balance Sheet & Forecast'!F65 -> 0 | G50: ='Balance Sheet & Forecast'!G65 -> 0 | I50: ='Balance Sheet & Forecast'!I65 -> 0 | J50: ='Balance Sheet & Forecast'!J65 -> 0 | K50: ='Balance Sheet & Forecast'!K65 -> 0 | L50: ='Balance Sheet & Forecast'!L65 -> 0 | M50: ='Balance Sheet & Forecast'!M65 -> 0
B52: INTERACTIVE CHARTS
B53: Revenue & Profitability Trajectory | I53: Cash Flow Generation Profile
B71: ── Helper Data (chart & delta source — do not edit)
B72: Compare Period Index | C72: =MATCH(F4,C75:L75,0) -> 5
B75: Period | C75: ='Income Statement & Forecast'!C4 -> 31.03.2021 | D75: ='Income Statement & Forecast'!D4 -> 31.03.2022 | E75: ='Income Statement & Forecast'!E4 -> 31.03.2023 | F75: ='Income Statement & Forecast'!F4 -> 31.03.2024 | G75: ='Income Statement & Forecast'!G4 -> 31.03.2025 | H75: ='Income Statement & Forecast'!I4 -> 31.03.2026E | I75: ='Income Statement & Forecast'!J4 -> 31.03.2027E | J75: ='Income Statement & Forecast'!K4 -> 31.03.2028E | K75: ='Income Statement & Forecast'!L4 -> 31.03.2029E | L75: ='Income Statement & Forecast'!M4 -> 31.03.2030E
B76: Revenue | C76: ='Income Statement & Forecast'!C10 -> 22015.84 | D76: ='Income Statement & Forecast'!D10 -> 29481.29 | E76: ='Income Statement & Forecast'!E10 -> 34875.07 | F76: ='Income Statement & Forecast'!F10 -> 36182.69 | G76: ='Income Statement & Forecast'!G10 -> 34478.23 | H76: ='Income Statement & Forecast'!I10 -> 36539.957 | I76: ='Income Statement & Forecast'!J10 -> 39465.154 | J76: ='Income Statement & Forecast'!K10 -> 42620.366 | K76: ='Income Statement & Forecast'!L10 -> 46023.995 | L76: ='Income Statement & Forecast'!M10 -> 49243.175
B77: EBITDA | C77: ='Income Statement & Forecast'!C18 -> 5158.65 | D77: ='Income Statement & Forecast'!D18 -> 5183.62 | E77: ='Income Statement & Forecast'!E18 -> 6646.32 | F77: ='Income Statement & Forecast'!F18 -> 8272.94 | G77: ='Income Statement & Forecast'!G18 -> 6578.82 | H77: ='Income Statement & Forecast'!I18 -> 6889.4925 | I77: ='Income Statement & Forecast'!J18 -> 7442.6519 | J77: ='Income Statement & Forecast'!K18 -> 8036.0641 | K77: ='Income Statement & Forecast'!L18 -> 8672.9492 | L77: ='Income Statement & Forecast'!M18 -> 9277.5556
B78: EBITDA Margin | C78: =C77/C76 -> 0.23431538 | D78: =D77/D76 -> 0.17582745 | E78: =E77/E76 -> 0.1905751 | F78: =F77/F76 -> 0.22864359 | G78: =G77/G76 -> 0.19081084 | H78: =H77/H76 -> 0.18854681 | I78: =I77/I76 -> 0.18858794 | J78: =J77/J76 -> 0.18854986 | ... L78: =L77/L76 -> 0.18840287
B79: PAT | C79: ='Income Statement & Forecast'!C31 -> 3206.75 | D79: ='Income Statement & Forecast'!D31 -> 3084.81 | E79: ='Income Statement & Forecast'!E31 -> 4195.33 | F79: ='Income Statement & Forecast'!F31 -> 5557.69 | G79: ='Income Statement & Forecast'!G31 -> 3709.71 | H79: ='Income Statement & Forecast'!I31 -> 4214.434 | I79: ='Income Statement & Forecast'!J31 -> 4549.7888 | J79: ='Income Statement & Forecast'!K31 -> 4908.8479 | K79: ='Income Statement & Forecast'!L31 -> 5293.4996 | L79: ='Income Statement & Forecast'!M31 -> 5649.3305
B80: PAT Margin | C80: =C79/C76 -> 0.14565649 | D80: =D79/D76 -> 0.10463619 | E80: =E79/E76 -> 0.12029596 | F80: =F79/F76 -> 0.1536008 | G80: =G79/G76 -> 0.10759572 | H80: =H79/H76 -> 0.11533768 | I80: =I79/I76 -> 0.11528623 | J80: =J79/J76 -> 0.11517611 | ... L80: =L79/L76 -> 0.11472312
B81: EPS | C81: ='Income Statement & Forecast'!C47 -> 32.73 | D81: ='Income Statement & Forecast'!D47 -> 31.59 | E81: ='Income Statement & Forecast'!E47 -> 42.83 | F81: ='Income Statement & Forecast'!F47 -> 56.95 | G81: ='Income Statement & Forecast'!G47 -> 38.25 | H81: ='Income Statement & Forecast'!I47 -> 43.431693 | I81: ='Income Statement & Forecast'!J47 -> 46.887679 | J81: ='Income Statement & Forecast'!K47 -> 50.58795 | K81: ='Income Statement & Forecast'!L47 -> 54.551964 | L81: ='Income Statement & Forecast'!M47 -> 58.218966
B82: ROE | C82: ='Income Statement & Forecast'!C31/'Balance Sheet & Forecast'!C41 -> 0.24240031 | D82: ='Income Statement & Forecast'!D31/'Balance Sheet & Forecast'!D41 -> 0.21725406 | E82: ='Income Statement & Forecast'!E31/'Balance Sheet & Forecast'!E41 -> 0.25509899 | F82: ='Income Statement & Forecast'!F31/'Balance Sheet & Forecast'!F41 -> 0.28612961 | G82: ='Income Statement & Forecast'!G31/'Balance Sheet & Forecast'!G41 -> 0.18493947 | H82: ='Income Statement & Forecast'!I31/'Balance Sheet & Forecast'!I41 -> 0.19764381 | I82: ='Income Statement & Forecast'!J31/'Balance Sheet & Forecast'!J41 -> 0.20053443 | J82: ='Income Statement & Forecast'!K31/'Balance Sheet & Forecast'!K41 -> 0.20317262 | K82: ='Income Statement & Forecast'!L31/'Balance Sheet & Forecast'!L41 -> 0.20558062 | L82: ='Income Statement & Forecast'!M31/'Balance Sheet & Forecast'!M41 -> 0.20585073
B83: CFO | C83: ='Cash Flow Statement & Forecast'!C43 -> 3683.35 | D83: ='Cash Flow Statement & Forecast'!D43 -> 986.49 | E83: ='Cash Flow Statement & Forecast'!E43 -> 4193.43 | F83: ='Cash Flow Statement & Forecast'!F43 -> 6103.6 | G83: ='Cash Flow Statement & Forecast'!G43 -> 4423.96 | H83: ='Cash Flow Statement & Forecast'!I43 -> 4408.4168 | I83: ='Cash Flow Statement & Forecast'!J43 -> 5189.2576 | J83: ='Cash Flow Statement & Forecast'!K43 -> 5604.1282 | K83: ='Cash Flow Statement & Forecast'!L43 -> 6049.289 | L83: ='Cash Flow Statement & Forecast'!M43 -> 6570.8818
B84: Capex (abs) | C84: =-'Cash Flow Statement & Forecast'!C45 -> 281.87 | D84: =-'Cash Flow Statement & Forecast'!D45 -> 538.24 | E84: =-'Cash Flow Statement & Forecast'!E45 -> 1273.37 | F84: =-'Cash Flow Statement & Forecast'!F45 -> 2199.01 | G84: =-'Cash Flow Statement & Forecast'!G45 -> 1805.32 | H84: =-'Cash Flow Statement & Forecast'!I45 -> 2515.797 | I84: =-'Cash Flow Statement & Forecast'!J45 -> 2717.0608 | J84: =-'Cash Flow Statement & Forecast'!K45 -> 2515.222 | K84: =-'Cash Flow Statement & Forecast'!L45 -> 2716.4397 | L84: =-'Cash Flow Statement & Forecast'!M45 -> 2906.5905
B85: FCF | C85: =C83-C84 -> 3401.48 | D85: =D83-D84 -> 448.25 | E85: =E83-E84 -> 2920.06 | F85: =F83-F84 -> 3904.59 | G85: =G83-G84 -> 2618.64 | H85: =H83-H84 -> 1892.6198 | I85: =I83-I84 -> 2472.1968 | J85: =J83-J84 -> 3088.9063 | ... L85: =L83-L84 -> 3664.2913
B86: Dividends (abs) | C86: =-'Cash Flow Statement & Forecast'!C70 -> 499.35 | D86: =-'Cash Flow Statement & Forecast'!D70 -> 1762.8 | E86: =-'Cash Flow Statement & Forecast'!E70 -> 1936.05 | F86: =-'Cash Flow Statement & Forecast'!F70 -> 2550.88 | G86: =-'Cash Flow Statement & Forecast'!G70 -> 3140.21 | H86: =-'Cash Flow Statement & Forecast'!I70 -> 2950.1038 | I86: =-'Cash Flow Statement & Forecast'!J70 -> 3184.8521 | J86: =-'Cash Flow Statement & Forecast'!K70 -> 3436.1936 | K86: =-'Cash Flow Statement & Forecast'!L70 -> 3705.4497 | L86: =-'Cash Flow Statement & Forecast'!M70 -> 3954.5313

Sheet __tracelight_scratchpad__
